{
    "all": {
        "oneDollar": {
            "donors": 2386,
            "receipts": 2386,
            "amt": 2386
        },
        "oneToTwoHundredDollars": {
            "donors": 7994,
            "receipts": 9291,
            "amt": 134509.91
        },
        "twoHundredToOneThousandDollars": {
            "donors": 151,
            "receipts": 271,
            "amt": 55366
        },
        "oneThousandToTwentyEightHundredDollars": {
            "donors": 193,
            "receipts": 198,
            "amt": 270654
        },
        "twentyEightHundredDollars": {
            "donors": 333,
            "receipts": 338,
            "amt": 935215
        },
        "full2020PrimaryCycle": {
            "donors": 11057,
            "receipts": 12484,
            "amt": 1398130.91
        },
        "pre2019": {
            "donors": 0,
            "receipts": 0,
            "amt": 0
        },
        "q12019": {
            "donors": 0,
            "receipts": 0,
            "amt": 0
        },
        "q22019": {
            "donors": 6590,
            "receipts": 6871,
            "amt": 1062256.84
        },
        "q32019": {
            "donors": 4855,
            "receipts": 5600,
            "amt": 330194.07
        },
        "q42019": {
            "donors": 5,
            "receipts": 6,
            "amt": 5610
        },
        "q12020": {
            "donors": 4,
            "receipts": 7,
            "amt": 70
        },
        "debate1": {
            "donors": 3821,
            "receipts": 3915,
            "amt": 252957.3
        },
        "debate2": {
            "donors": 3267,
            "receipts": 3384,
            "amt": 858873.11
        },
        "debate3": {
            "donors": 4134,
            "receipts": 4417,
            "amt": 137897.8
        },
        "debate4": {
            "donors": 702,
            "receipts": 755,
            "amt": 142722.7
        },
        "debate5": {
            "donors": 3,
            "receipts": 3,
            "amt": 5601
        },
        "debate6": {
            "donors": 1,
            "receipts": 1,
            "amt": 3
        },
        "debate7": {
            "donors": 2,
            "receipts": 2,
            "amt": 6
        },
        "inState": {
            "donors": 6489,
            "receipts": 7267,
            "amt": 1091110.78
        },
        "outOfState": {
            "donors": 4568,
            "receipts": 5217,
            "amt": 307020.13
        },
        "prior": {
            "donors": 64,
            "receipts": 112,
            "amt": 92855
        },
        "loyal": {
            "donors": 7125,
            "receipts": 7709,
            "amt": 1039185.69
        },
        "donor2016": {
            "donors": 1522,
            "receipts": 1968,
            "amt": 211864.98
        },
        "clinton2016": {
            "donors": 503,
            "receipts": 669,
            "amt": 184969.49
        },
        "sanders2016": {
            "donors": 1144,
            "receipts": 1486,
            "amt": 36876.49
        },
        "obama2012": {
            "donors": 120,
            "receipts": 171,
            "amt": 30278
        },
        "traitor": {
            "donors": 242,
            "receipts": 274,
            "amt": 43234
        },
        "elite": {
            "donors": 5095,
            "receipts": 6196,
            "amt": 1134715.66
        },
        "party": {
            "donors": 4426,
            "receipts": 5411,
            "amt": 444792.91
        },
        "nationalParty": {
            "donors": 4264,
            "receipts": 5223,
            "amt": 412468.91
        },
        "stateParty": {
            "donors": 1838,
            "receipts": 2434,
            "amt": 159466.64
        },
        "localParty": {
            "donors": 301,
            "receipts": 413,
            "amt": 34163.44
        },
        "competitorEndorsement": {
            "donors": 0,
            "receipts": 0,
            "amt": 0
        },
        "congressionalEndorsement": {
            "donors": 0,
            "receipts": 0,
            "amt": 0
        },
        "senateEndorsement": {
            "donors": 0,
            "receipts": 0,
            "amt": 0
        },
        "houseEndorsement": {
            "donors": 0,
            "receipts": 0,
            "amt": 0
        }
    },
    "dayOneLaunch": {
        "oneDollar": {
            "donors": 27,
            "receipts": 27,
            "amt": 27
        },
        "oneToTwoHundredDollars": {
            "donors": 173,
            "receipts": 281,
            "amt": 4827.05
        },
        "twoHundredToOneThousandDollars": {
            "donors": 11,
            "receipts": 45,
            "amt": 4050
        },
        "oneThousandToTwentyEightHundredDollars": {
            "donors": 3,
            "receipts": 4,
            "amt": 4203
        },
        "twentyEightHundredDollars": {
            "donors": 0,
            "receipts": 0,
            "amt": 0
        },
        "full2020PrimaryCycle": {
            "donors": 214,
            "receipts": 357,
            "amt": 13107.05
        },
        "pre2019": {
            "donors": 0,
            "receipts": 0,
            "amt": 0
        },
        "q12019": {
            "donors": 0,
            "receipts": 0,
            "amt": 0
        },
        "q22019": {
            "donors": 214,
            "receipts": 281,
            "amt": 11049.48
        },
        "q32019": {
            "donors": 37,
            "receipts": 76,
            "amt": 2057.57
        },
        "q42019": {
            "donors": 0,
            "receipts": 0,
            "amt": 0
        },
        "q12020": {
            "donors": 0,
            "receipts": 0,
            "amt": 0
        },
        "debate1": {
            "donors": 214,
            "receipts": 239,
            "amt": 9998
        },
        "debate2": {
            "donors": 34,
            "receipts": 50,
            "amt": 1229.05
        },
        "debate3": {
            "donors": 33,
            "receipts": 49,
            "amt": 1316
        },
        "debate4": {
            "donors": 13,
            "receipts": 19,
            "amt": 564
        },
        "debate5": {
            "donors": 0,
            "receipts": 0,
            "amt": 0
        },
        "debate6": {
            "donors": 0,
            "receipts": 0,
            "amt": 0
        },
        "debate7": {
            "donors": 0,
            "receipts": 0,
            "amt": 0
        },
        "inState": {
            "donors": 129,
            "receipts": 199,
            "amt": 9849.11
        },
        "outOfState": {
            "donors": 85,
            "receipts": 158,
            "amt": 3257.94
        },
        "prior": {
            "donors": 6,
            "receipts": 23,
            "amt": 1503
        },
        "loyal": {
            "donors": 49,
            "receipts": 68,
            "amt": 3871
        },
        "donor2016": {
            "donors": 88,
            "receipts": 159,
            "amt": 7090.05
        },
        "clinton2016": {
            "donors": 32,
            "receipts": 68,
            "amt": 4591.94
        },
        "sanders2016": {
            "donors": 65,
            "receipts": 105,
            "amt": 2824.11
        },
        "obama2012": {
            "donors": 12,
            "receipts": 27,
            "amt": 3353
        },
        "traitor": {
            "donors": 8,
            "receipts": 10,
            "amt": 1507
        },
        "elite": {
            "donors": 191,
            "receipts": 334,
            "amt": 12766.05
        },
        "party": {
            "donors": 176,
            "receipts": 308,
            "amt": 11246.05
        },
        "nationalParty": {
            "donors": 173,
            "receipts": 304,
            "amt": 11168.05
        },
        "stateParty": {
            "donors": 99,
            "receipts": 189,
            "amt": 6295.94
        },
        "localParty": {
            "donors": 11,
            "receipts": 17,
            "amt": 346.94
        },
        "competitorEndorsement": {
            "donors": 0,
            "receipts": 0,
            "amt": 0
        },
        "congressionalEndorsement": {
            "donors": 0,
            "receipts": 0,
            "amt": 0
        },
        "senateEndorsement": {
            "donors": 0,
            "receipts": 0,
            "amt": 0
        },
        "houseEndorsement": {
            "donors": 0,
            "receipts": 0,
            "amt": 0
        }
    },
    "weekOneLaunch": {
        "oneDollar": {
            "donors": 51,
            "receipts": 51,
            "amt": 51
        },
        "oneToTwoHundredDollars": {
            "donors": 399,
            "receipts": 668,
            "amt": 10518.05
        },
        "twoHundredToOneThousandDollars": {
            "donors": 20,
            "receipts": 95,
            "amt": 7832
        },
        "oneThousandToTwentyEightHundredDollars": {
            "donors": 7,
            "receipts": 9,
            "amt": 9803
        },
        "twentyEightHundredDollars": {
            "donors": 7,
            "receipts": 7,
            "amt": 19600
        },
        "full2020PrimaryCycle": {
            "donors": 484,
            "receipts": 830,
            "amt": 47804.05
        },
        "pre2019": {
            "donors": 0,
            "receipts": 0,
            "amt": 0
        },
        "q12019": {
            "donors": 0,
            "receipts": 0,
            "amt": 0
        },
        "q22019": {
            "donors": 484,
            "receipts": 623,
            "amt": 43420.48
        },
        "q32019": {
            "donors": 90,
            "receipts": 207,
            "amt": 4383.57
        },
        "q42019": {
            "donors": 0,
            "receipts": 0,
            "amt": 0
        },
        "q12020": {
            "donors": 0,
            "receipts": 0,
            "amt": 0
        },
        "debate1": {
            "donors": 484,
            "receipts": 534,
            "amt": 40129
        },
        "debate2": {
            "donors": 82,
            "receipts": 108,
            "amt": 3710.05
        },
        "debate3": {
            "donors": 76,
            "receipts": 131,
            "amt": 2765
        },
        "debate4": {
            "donors": 38,
            "receipts": 57,
            "amt": 1200
        },
        "debate5": {
            "donors": 0,
            "receipts": 0,
            "amt": 0
        },
        "debate6": {
            "donors": 0,
            "receipts": 0,
            "amt": 0
        },
        "debate7": {
            "donors": 0,
            "receipts": 0,
            "amt": 0
        },
        "inState": {
            "donors": 279,
            "receipts": 475,
            "amt": 40612.11
        },
        "outOfState": {
            "donors": 205,
            "receipts": 355,
            "amt": 7191.94
        },
        "prior": {
            "donors": 19,
            "receipts": 57,
            "amt": 10690
        },
        "loyal": {
            "donors": 124,
            "receipts": 208,
            "amt": 28654
        },
        "donor2016": {
            "donors": 187,
            "receipts": 355,
            "amt": 13469.05
        },
        "clinton2016": {
            "donors": 72,
            "receipts": 151,
            "amt": 9167.94
        },
        "sanders2016": {
            "donors": 139,
            "receipts": 251,
            "amt": 5153.11
        },
        "obama2012": {
            "donors": 26,
            "receipts": 52,
            "amt": 5325
        },
        "traitor": {
            "donors": 16,
            "receipts": 23,
            "amt": 4335
        },
        "elite": {
            "donors": 408,
            "receipts": 735,
            "amt": 46426.05
        },
        "party": {
            "donors": 375,
            "receipts": 680,
            "amt": 26376.05
        },
        "nationalParty": {
            "donors": 365,
            "receipts": 660,
            "amt": 25076.05
        },
        "stateParty": {
            "donors": 224,
            "receipts": 444,
            "amt": 14479.94
        },
        "localParty": {
            "donors": 30,
            "receipts": 53,
            "amt": 811.94
        },
        "competitorEndorsement": {
            "donors": 0,
            "receipts": 0,
            "amt": 0
        },
        "congressionalEndorsement": {
            "donors": 0,
            "receipts": 0,
            "amt": 0
        },
        "senateEndorsement": {
            "donors": 0,
            "receipts": 0,
            "amt": 0
        },
        "houseEndorsement": {
            "donors": 0,
            "receipts": 0,
            "amt": 0
        }
    },
    "firstTime": {
        "oneDollar": {
            "donors": 1146,
            "receipts": 1146,
            "amt": 1146
        },
        "oneToTwoHundredDollars": {
            "donors": 4189,
            "receipts": 4465,
            "amt": 64879.74
        },
        "twoHundredToOneThousandDollars": {
            "donors": 9,
            "receipts": 13,
            "amt": 3372
        },
        "oneThousandToTwentyEightHundredDollars": {
            "donors": 29,
            "receipts": 29,
            "amt": 45200
        },
        "twentyEightHundredDollars": {
            "donors": 39,
            "receipts": 39,
            "amt": 109200
        },
        "full2020PrimaryCycle": {
            "donors": 5412,
            "receipts": 5692,
            "amt": 223797.74
        },
        "pre2019": {
            "donors": 0,
            "receipts": 0,
            "amt": 0
        },
        "q12019": {
            "donors": 0,
            "receipts": 0,
            "amt": 0
        },
        "q22019": {
            "donors": 3982,
            "receipts": 4030,
            "amt": 170930.33
        },
        "q32019": {
            "donors": 1516,
            "receipts": 1661,
            "amt": 52864.41
        },
        "q42019": {
            "donors": 0,
            "receipts": 0,
            "amt": 0
        },
        "q12020": {
            "donors": 1,
            "receipts": 1,
            "amt": 3
        },
        "debate1": {
            "donors": 2533,
            "receipts": 2551,
            "amt": 48007
        },
        "debate2": {
            "donors": 1571,
            "receipts": 1595,
            "amt": 129619.33
        },
        "debate3": {
            "donors": 1317,
            "receipts": 1360,
            "amt": 23173.41
        },
        "debate4": {
            "donors": 184,
            "receipts": 185,
            "amt": 22995
        },
        "debate5": {
            "donors": 0,
            "receipts": 0,
            "amt": 0
        },
        "debate6": {
            "donors": 0,
            "receipts": 0,
            "amt": 0
        },
        "debate7": {
            "donors": 0,
            "receipts": 0,
            "amt": 0
        },
        "inState": {
            "donors": 4127,
            "receipts": 4346,
            "amt": 176755.64
        },
        "outOfState": {
            "donors": 1285,
            "receipts": 1346,
            "amt": 47042.1
        },
        "prior": {
            "donors": 0,
            "receipts": 0,
            "amt": 0
        },
        "loyal": {
            "donors": 5412,
            "receipts": 5692,
            "amt": 223797.74
        },
        "donor2016": {
            "donors": 0,
            "receipts": 0,
            "amt": 0
        },
        "clinton2016": {
            "donors": 0,
            "receipts": 0,
            "amt": 0
        },
        "sanders2016": {
            "donors": 0,
            "receipts": 0,
            "amt": 0
        },
        "obama2012": {
            "donors": 0,
            "receipts": 0,
            "amt": 0
        },
        "traitor": {
            "donors": 0,
            "receipts": 0,
            "amt": 0
        },
        "elite": {
            "donors": 0,
            "receipts": 0,
            "amt": 0
        },
        "party": {
            "donors": 0,
            "receipts": 0,
            "amt": 0
        },
        "nationalParty": {
            "donors": 0,
            "receipts": 0,
            "amt": 0
        },
        "stateParty": {
            "donors": 0,
            "receipts": 0,
            "amt": 0
        },
        "localParty": {
            "donors": 0,
            "receipts": 0,
            "amt": 0
        },
        "competitorEndorsement": {
            "donors": 0,
            "receipts": 0,
            "amt": 0
        },
        "congressionalEndorsement": {
            "donors": 0,
            "receipts": 0,
            "amt": 0
        },
        "senateEndorsement": {
            "donors": 0,
            "receipts": 0,
            "amt": 0
        },
        "houseEndorsement": {
            "donors": 0,
            "receipts": 0,
            "amt": 0
        }
    },
    "prior": {
        "oneDollar": {
            "donors": 3,
            "receipts": 3,
            "amt": 3
        },
        "oneToTwoHundredDollars": {
            "donors": 23,
            "receipts": 48,
            "amt": 1199
        },
        "twoHundredToOneThousandDollars": {
            "donors": 5,
            "receipts": 27,
            "amt": 2050
        },
        "oneThousandToTwentyEightHundredDollars": {
            "donors": 2,
            "receipts": 2,
            "amt": 2800
        },
        "twentyEightHundredDollars": {
            "donors": 31,
            "receipts": 32,
            "amt": 86803
        },
        "full2020PrimaryCycle": {
            "donors": 64,
            "receipts": 112,
            "amt": 92855
        },
        "pre2019": {
            "donors": 0,
            "receipts": 0,
            "amt": 0
        },
        "q12019": {
            "donors": 0,
            "receipts": 0,
            "amt": 0
        },
        "q22019": {
            "donors": 51,
            "receipts": 67,
            "amt": 85287
        },
        "q32019": {
            "donors": 24,
            "receipts": 45,
            "amt": 7568
        },
        "q42019": {
            "donors": 0,
            "receipts": 0,
            "amt": 0
        },
        "q12020": {
            "donors": 0,
            "receipts": 0,
            "amt": 0
        },
        "debate1": {
            "donors": 35,
            "receipts": 41,
            "amt": 41864
        },
        "debate2": {
            "donors": 26,
            "receipts": 29,
            "amt": 46333
        },
        "debate3": {
            "donors": 16,
            "receipts": 25,
            "amt": 3751
        },
        "debate4": {
            "donors": 13,
            "receipts": 17,
            "amt": 907
        },
        "debate5": {
            "donors": 0,
            "receipts": 0,
            "amt": 0
        },
        "debate6": {
            "donors": 0,
            "receipts": 0,
            "amt": 0
        },
        "debate7": {
            "donors": 0,
            "receipts": 0,
            "amt": 0
        },
        "inState": {
            "donors": 53,
            "receipts": 87,
            "amt": 80047
        },
        "outOfState": {
            "donors": 11,
            "receipts": 25,
            "amt": 12808
        },
        "prior": {
            "donors": 64,
            "receipts": 112,
            "amt": 92855
        },
        "loyal": {
            "donors": 27,
            "receipts": 42,
            "amt": 45252
        },
        "donor2016": {
            "donors": 21,
            "receipts": 48,
            "amt": 29614
        },
        "clinton2016": {
            "donors": 15,
            "receipts": 23,
            "amt": 28333
        },
        "sanders2016": {
            "donors": 7,
            "receipts": 32,
            "amt": 1358
        },
        "obama2012": {
            "donors": 2,
            "receipts": 2,
            "amt": 1003
        },
        "traitor": {
            "donors": 4,
            "receipts": 5,
            "amt": 5950
        },
        "elite": {
            "donors": 64,
            "receipts": 112,
            "amt": 92855
        },
        "party": {
            "donors": 46,
            "receipts": 87,
            "amt": 48603
        },
        "nationalParty": {
            "donors": 44,
            "receipts": 81,
            "amt": 45788
        },
        "stateParty": {
            "donors": 29,
            "receipts": 65,
            "amt": 27897
        },
        "localParty": {
            "donors": 10,
            "receipts": 13,
            "amt": 9465
        },
        "competitorEndorsement": {
            "donors": 0,
            "receipts": 0,
            "amt": 0
        },
        "congressionalEndorsement": {
            "donors": 0,
            "receipts": 0,
            "amt": 0
        },
        "senateEndorsement": {
            "donors": 0,
            "receipts": 0,
            "amt": 0
        },
        "houseEndorsement": {
            "donors": 0,
            "receipts": 0,
            "amt": 0
        }
    },
    "priorCampaign": {
        "oneDollar": {
            "donors": 0,
            "receipts": 0,
            "amt": 0
        },
        "oneToTwoHundredDollars": {
            "donors": 0,
            "receipts": 0,
            "amt": 0
        },
        "twoHundredToOneThousandDollars": {
            "donors": 0,
            "receipts": 0,
            "amt": 0
        },
        "oneThousandToTwentyEightHundredDollars": {
            "donors": 0,
            "receipts": 0,
            "amt": 0
        },
        "twentyEightHundredDollars": {
            "donors": 0,
            "receipts": 0,
            "amt": 0
        },
        "full2020PrimaryCycle": {
            "donors": 0,
            "receipts": 0,
            "amt": 0
        },
        "pre2019": {
            "donors": 0,
            "receipts": 0,
            "amt": 0
        },
        "q12019": {
            "donors": 0,
            "receipts": 0,
            "amt": 0
        },
        "q22019": {
            "donors": 0,
            "receipts": 0,
            "amt": 0
        },
        "q32019": {
            "donors": 0,
            "receipts": 0,
            "amt": 0
        },
        "q42019": {
            "donors": 0,
            "receipts": 0,
            "amt": 0
        },
        "q12020": {
            "donors": 0,
            "receipts": 0,
            "amt": 0
        },
        "debate1": {
            "donors": 0,
            "receipts": 0,
            "amt": 0
        },
        "debate2": {
            "donors": 0,
            "receipts": 0,
            "amt": 0
        },
        "debate3": {
            "donors": 0,
            "receipts": 0,
            "amt": 0
        },
        "debate4": {
            "donors": 0,
            "receipts": 0,
            "amt": 0
        },
        "debate5": {
            "donors": 0,
            "receipts": 0,
            "amt": 0
        },
        "debate6": {
            "donors": 0,
            "receipts": 0,
            "amt": 0
        },
        "debate7": {
            "donors": 0,
            "receipts": 0,
            "amt": 0
        },
        "inState": {
            "donors": 0,
            "receipts": 0,
            "amt": 0
        },
        "outOfState": {
            "donors": 0,
            "receipts": 0,
            "amt": 0
        },
        "prior": {
            "donors": 0,
            "receipts": 0,
            "amt": 0
        },
        "loyal": {
            "donors": 0,
            "receipts": 0,
            "amt": 0
        },
        "donor2016": {
            "donors": 0,
            "receipts": 0,
            "amt": 0
        },
        "clinton2016": {
            "donors": 0,
            "receipts": 0,
            "amt": 0
        },
        "sanders2016": {
            "donors": 0,
            "receipts": 0,
            "amt": 0
        },
        "obama2012": {
            "donors": 0,
            "receipts": 0,
            "amt": 0
        },
        "traitor": {
            "donors": 0,
            "receipts": 0,
            "amt": 0
        },
        "elite": {
            "donors": 0,
            "receipts": 0,
            "amt": 0
        },
        "party": {
            "donors": 0,
            "receipts": 0,
            "amt": 0
        },
        "nationalParty": {
            "donors": 0,
            "receipts": 0,
            "amt": 0
        },
        "stateParty": {
            "donors": 0,
            "receipts": 0,
            "amt": 0
        },
        "localParty": {
            "donors": 0,
            "receipts": 0,
            "amt": 0
        },
        "competitorEndorsement": {
            "donors": 0,
            "receipts": 0,
            "amt": 0
        },
        "congressionalEndorsement": {
            "donors": 0,
            "receipts": 0,
            "amt": 0
        },
        "senateEndorsement": {
            "donors": 0,
            "receipts": 0,
            "amt": 0
        },
        "houseEndorsement": {
            "donors": 0,
            "receipts": 0,
            "amt": 0
        }
    },
    "priorLeadershipPac": {
        "oneDollar": {
            "donors": 3,
            "receipts": 3,
            "amt": 3
        },
        "oneToTwoHundredDollars": {
            "donors": 23,
            "receipts": 48,
            "amt": 1199
        },
        "twoHundredToOneThousandDollars": {
            "donors": 5,
            "receipts": 27,
            "amt": 2050
        },
        "oneThousandToTwentyEightHundredDollars": {
            "donors": 2,
            "receipts": 2,
            "amt": 2800
        },
        "twentyEightHundredDollars": {
            "donors": 31,
            "receipts": 32,
            "amt": 86803
        },
        "full2020PrimaryCycle": {
            "donors": 64,
            "receipts": 112,
            "amt": 92855
        },
        "pre2019": {
            "donors": 0,
            "receipts": 0,
            "amt": 0
        },
        "q12019": {
            "donors": 0,
            "receipts": 0,
            "amt": 0
        },
        "q22019": {
            "donors": 51,
            "receipts": 67,
            "amt": 85287
        },
        "q32019": {
            "donors": 24,
            "receipts": 45,
            "amt": 7568
        },
        "q42019": {
            "donors": 0,
            "receipts": 0,
            "amt": 0
        },
        "q12020": {
            "donors": 0,
            "receipts": 0,
            "amt": 0
        },
        "debate1": {
            "donors": 35,
            "receipts": 41,
            "amt": 41864
        },
        "debate2": {
            "donors": 26,
            "receipts": 29,
            "amt": 46333
        },
        "debate3": {
            "donors": 16,
            "receipts": 25,
            "amt": 3751
        },
        "debate4": {
            "donors": 13,
            "receipts": 17,
            "amt": 907
        },
        "debate5": {
            "donors": 0,
            "receipts": 0,
            "amt": 0
        },
        "debate6": {
            "donors": 0,
            "receipts": 0,
            "amt": 0
        },
        "debate7": {
            "donors": 0,
            "receipts": 0,
            "amt": 0
        },
        "inState": {
            "donors": 53,
            "receipts": 87,
            "amt": 80047
        },
        "outOfState": {
            "donors": 11,
            "receipts": 25,
            "amt": 12808
        },
        "prior": {
            "donors": 64,
            "receipts": 112,
            "amt": 92855
        },
        "loyal": {
            "donors": 27,
            "receipts": 42,
            "amt": 45252
        },
        "donor2016": {
            "donors": 21,
            "receipts": 48,
            "amt": 29614
        },
        "clinton2016": {
            "donors": 15,
            "receipts": 23,
            "amt": 28333
        },
        "sanders2016": {
            "donors": 7,
            "receipts": 32,
            "amt": 1358
        },
        "obama2012": {
            "donors": 2,
            "receipts": 2,
            "amt": 1003
        },
        "traitor": {
            "donors": 4,
            "receipts": 5,
            "amt": 5950
        },
        "elite": {
            "donors": 64,
            "receipts": 112,
            "amt": 92855
        },
        "party": {
            "donors": 46,
            "receipts": 87,
            "amt": 48603
        },
        "nationalParty": {
            "donors": 44,
            "receipts": 81,
            "amt": 45788
        },
        "stateParty": {
            "donors": 29,
            "receipts": 65,
            "amt": 27897
        },
        "localParty": {
            "donors": 10,
            "receipts": 13,
            "amt": 9465
        },
        "competitorEndorsement": {
            "donors": 0,
            "receipts": 0,
            "amt": 0
        },
        "congressionalEndorsement": {
            "donors": 0,
            "receipts": 0,
            "amt": 0
        },
        "senateEndorsement": {
            "donors": 0,
            "receipts": 0,
            "amt": 0
        },
        "houseEndorsement": {
            "donors": 0,
            "receipts": 0,
            "amt": 0
        }
    },
    "endorsement": {
        "oneDollar": {
            "donors": 0,
            "receipts": 0,
            "amt": 0
        },
        "oneToTwoHundredDollars": {
            "donors": 0,
            "receipts": 0,
            "amt": 0
        },
        "twoHundredToOneThousandDollars": {
            "donors": 0,
            "receipts": 0,
            "amt": 0
        },
        "oneThousandToTwentyEightHundredDollars": {
            "donors": 0,
            "receipts": 0,
            "amt": 0
        },
        "twentyEightHundredDollars": {
            "donors": 0,
            "receipts": 0,
            "amt": 0
        },
        "full2020PrimaryCycle": {
            "donors": 0,
            "receipts": 0,
            "amt": 0
        },
        "pre2019": {
            "donors": 0,
            "receipts": 0,
            "amt": 0
        },
        "q12019": {
            "donors": 0,
            "receipts": 0,
            "amt": 0
        },
        "q22019": {
            "donors": 0,
            "receipts": 0,
            "amt": 0
        },
        "q32019": {
            "donors": 0,
            "receipts": 0,
            "amt": 0
        },
        "q42019": {
            "donors": 0,
            "receipts": 0,
            "amt": 0
        },
        "q12020": {
            "donors": 0,
            "receipts": 0,
            "amt": 0
        },
        "debate1": {
            "donors": 0,
            "receipts": 0,
            "amt": 0
        },
        "debate2": {
            "donors": 0,
            "receipts": 0,
            "amt": 0
        },
        "debate3": {
            "donors": 0,
            "receipts": 0,
            "amt": 0
        },
        "debate4": {
            "donors": 0,
            "receipts": 0,
            "amt": 0
        },
        "debate5": {
            "donors": 0,
            "receipts": 0,
            "amt": 0
        },
        "debate6": {
            "donors": 0,
            "receipts": 0,
            "amt": 0
        },
        "debate7": {
            "donors": 0,
            "receipts": 0,
            "amt": 0
        },
        "inState": {
            "donors": 0,
            "receipts": 0,
            "amt": 0
        },
        "outOfState": {
            "donors": 0,
            "receipts": 0,
            "amt": 0
        },
        "prior": {
            "donors": 0,
            "receipts": 0,
            "amt": 0
        },
        "loyal": {
            "donors": 0,
            "receipts": 0,
            "amt": 0
        },
        "donor2016": {
            "donors": 0,
            "receipts": 0,
            "amt": 0
        },
        "clinton2016": {
            "donors": 0,
            "receipts": 0,
            "amt": 0
        },
        "sanders2016": {
            "donors": 0,
            "receipts": 0,
            "amt": 0
        },
        "obama2012": {
            "donors": 0,
            "receipts": 0,
            "amt": 0
        },
        "traitor": {
            "donors": 0,
            "receipts": 0,
            "amt": 0
        },
        "elite": {
            "donors": 0,
            "receipts": 0,
            "amt": 0
        },
        "party": {
            "donors": 0,
            "receipts": 0,
            "amt": 0
        },
        "nationalParty": {
            "donors": 0,
            "receipts": 0,
            "amt": 0
        },
        "stateParty": {
            "donors": 0,
            "receipts": 0,
            "amt": 0
        },
        "localParty": {
            "donors": 0,
            "receipts": 0,
            "amt": 0
        },
        "competitorEndorsement": {
            "donors": 0,
            "receipts": 0,
            "amt": 0
        },
        "congressionalEndorsement": {
            "donors": 0,
            "receipts": 0,
            "amt": 0
        },
        "senateEndorsement": {
            "donors": 0,
            "receipts": 0,
            "amt": 0
        },
        "houseEndorsement": {
            "donors": 0,
            "receipts": 0,
            "amt": 0
        }
    },
    "endorsementPre": {
        "oneDollar": {
            "donors": 0,
            "receipts": 0,
            "amt": 0
        },
        "oneToTwoHundredDollars": {
            "donors": 0,
            "receipts": 0,
            "amt": 0
        },
        "twoHundredToOneThousandDollars": {
            "donors": 0,
            "receipts": 0,
            "amt": 0
        },
        "oneThousandToTwentyEightHundredDollars": {
            "donors": 0,
            "receipts": 0,
            "amt": 0
        },
        "twentyEightHundredDollars": {
            "donors": 0,
            "receipts": 0,
            "amt": 0
        },
        "full2020PrimaryCycle": {
            "donors": 0,
            "receipts": 0,
            "amt": 0
        },
        "pre2019": {
            "donors": 0,
            "receipts": 0,
            "amt": 0
        },
        "q12019": {
            "donors": 0,
            "receipts": 0,
            "amt": 0
        },
        "q22019": {
            "donors": 0,
            "receipts": 0,
            "amt": 0
        },
        "q32019": {
            "donors": 0,
            "receipts": 0,
            "amt": 0
        },
        "q42019": {
            "donors": 0,
            "receipts": 0,
            "amt": 0
        },
        "q12020": {
            "donors": 0,
            "receipts": 0,
            "amt": 0
        },
        "debate1": {
            "donors": 0,
            "receipts": 0,
            "amt": 0
        },
        "debate2": {
            "donors": 0,
            "receipts": 0,
            "amt": 0
        },
        "debate3": {
            "donors": 0,
            "receipts": 0,
            "amt": 0
        },
        "debate4": {
            "donors": 0,
            "receipts": 0,
            "amt": 0
        },
        "debate5": {
            "donors": 0,
            "receipts": 0,
            "amt": 0
        },
        "debate6": {
            "donors": 0,
            "receipts": 0,
            "amt": 0
        },
        "debate7": {
            "donors": 0,
            "receipts": 0,
            "amt": 0
        },
        "inState": {
            "donors": 0,
            "receipts": 0,
            "amt": 0
        },
        "outOfState": {
            "donors": 0,
            "receipts": 0,
            "amt": 0
        },
        "prior": {
            "donors": 0,
            "receipts": 0,
            "amt": 0
        },
        "loyal": {
            "donors": 0,
            "receipts": 0,
            "amt": 0
        },
        "donor2016": {
            "donors": 0,
            "receipts": 0,
            "amt": 0
        },
        "clinton2016": {
            "donors": 0,
            "receipts": 0,
            "amt": 0
        },
        "sanders2016": {
            "donors": 0,
            "receipts": 0,
            "amt": 0
        },
        "obama2012": {
            "donors": 0,
            "receipts": 0,
            "amt": 0
        },
        "traitor": {
            "donors": 0,
            "receipts": 0,
            "amt": 0
        },
        "elite": {
            "donors": 0,
            "receipts": 0,
            "amt": 0
        },
        "party": {
            "donors": 0,
            "receipts": 0,
            "amt": 0
        },
        "nationalParty": {
            "donors": 0,
            "receipts": 0,
            "amt": 0
        },
        "stateParty": {
            "donors": 0,
            "receipts": 0,
            "amt": 0
        },
        "localParty": {
            "donors": 0,
            "receipts": 0,
            "amt": 0
        },
        "competitorEndorsement": {
            "donors": 0,
            "receipts": 0,
            "amt": 0
        },
        "congressionalEndorsement": {
            "donors": 0,
            "receipts": 0,
            "amt": 0
        },
        "senateEndorsement": {
            "donors": 0,
            "receipts": 0,
            "amt": 0
        },
        "houseEndorsement": {
            "donors": 0,
            "receipts": 0,
            "amt": 0
        }
    },
    "endorsementPost": {
        "oneDollar": {
            "donors": 0,
            "receipts": 0,
            "amt": 0
        },
        "oneToTwoHundredDollars": {
            "donors": 0,
            "receipts": 0,
            "amt": 0
        },
        "twoHundredToOneThousandDollars": {
            "donors": 0,
            "receipts": 0,
            "amt": 0
        },
        "oneThousandToTwentyEightHundredDollars": {
            "donors": 0,
            "receipts": 0,
            "amt": 0
        },
        "twentyEightHundredDollars": {
            "donors": 0,
            "receipts": 0,
            "amt": 0
        },
        "full2020PrimaryCycle": {
            "donors": 0,
            "receipts": 0,
            "amt": 0
        },
        "pre2019": {
            "donors": 0,
            "receipts": 0,
            "amt": 0
        },
        "q12019": {
            "donors": 0,
            "receipts": 0,
            "amt": 0
        },
        "q22019": {
            "donors": 0,
            "receipts": 0,
            "amt": 0
        },
        "q32019": {
            "donors": 0,
            "receipts": 0,
            "amt": 0
        },
        "q42019": {
            "donors": 0,
            "receipts": 0,
            "amt": 0
        },
        "q12020": {
            "donors": 0,
            "receipts": 0,
            "amt": 0
        },
        "debate1": {
            "donors": 0,
            "receipts": 0,
            "amt": 0
        },
        "debate2": {
            "donors": 0,
            "receipts": 0,
            "amt": 0
        },
        "debate3": {
            "donors": 0,
            "receipts": 0,
            "amt": 0
        },
        "debate4": {
            "donors": 0,
            "receipts": 0,
            "amt": 0
        },
        "debate5": {
            "donors": 0,
            "receipts": 0,
            "amt": 0
        },
        "debate6": {
            "donors": 0,
            "receipts": 0,
            "amt": 0
        },
        "debate7": {
            "donors": 0,
            "receipts": 0,
            "amt": 0
        },
        "inState": {
            "donors": 0,
            "receipts": 0,
            "amt": 0
        },
        "outOfState": {
            "donors": 0,
            "receipts": 0,
            "amt": 0
        },
        "prior": {
            "donors": 0,
            "receipts": 0,
            "amt": 0
        },
        "loyal": {
            "donors": 0,
            "receipts": 0,
            "amt": 0
        },
        "donor2016": {
            "donors": 0,
            "receipts": 0,
            "amt": 0
        },
        "clinton2016": {
            "donors": 0,
            "receipts": 0,
            "amt": 0
        },
        "sanders2016": {
            "donors": 0,
            "receipts": 0,
            "amt": 0
        },
        "obama2012": {
            "donors": 0,
            "receipts": 0,
            "amt": 0
        },
        "traitor": {
            "donors": 0,
            "receipts": 0,
            "amt": 0
        },
        "elite": {
            "donors": 0,
            "receipts": 0,
            "amt": 0
        },
        "party": {
            "donors": 0,
            "receipts": 0,
            "amt": 0
        },
        "nationalParty": {
            "donors": 0,
            "receipts": 0,
            "amt": 0
        },
        "stateParty": {
            "donors": 0,
            "receipts": 0,
            "amt": 0
        },
        "localParty": {
            "donors": 0,
            "receipts": 0,
            "amt": 0
        },
        "competitorEndorsement": {
            "donors": 0,
            "receipts": 0,
            "amt": 0
        },
        "congressionalEndorsement": {
            "donors": 0,
            "receipts": 0,
            "amt": 0
        },
        "senateEndorsement": {
            "donors": 0,
            "receipts": 0,
            "amt": 0
        },
        "houseEndorsement": {
            "donors": 0,
            "receipts": 0,
            "amt": 0
        }
    },
    "congressionalEndorsement": {
        "oneDollar": {
            "donors": 0,
            "receipts": 0,
            "amt": 0
        },
        "oneToTwoHundredDollars": {
            "donors": 0,
            "receipts": 0,
            "amt": 0
        },
        "twoHundredToOneThousandDollars": {
            "donors": 0,
            "receipts": 0,
            "amt": 0
        },
        "oneThousandToTwentyEightHundredDollars": {
            "donors": 0,
            "receipts": 0,
            "amt": 0
        },
        "twentyEightHundredDollars": {
            "donors": 0,
            "receipts": 0,
            "amt": 0
        },
        "full2020PrimaryCycle": {
            "donors": 0,
            "receipts": 0,
            "amt": 0
        },
        "pre2019": {
            "donors": 0,
            "receipts": 0,
            "amt": 0
        },
        "q12019": {
            "donors": 0,
            "receipts": 0,
            "amt": 0
        },
        "q22019": {
            "donors": 0,
            "receipts": 0,
            "amt": 0
        },
        "q32019": {
            "donors": 0,
            "receipts": 0,
            "amt": 0
        },
        "q42019": {
            "donors": 0,
            "receipts": 0,
            "amt": 0
        },
        "q12020": {
            "donors": 0,
            "receipts": 0,
            "amt": 0
        },
        "debate1": {
            "donors": 0,
            "receipts": 0,
            "amt": 0
        },
        "debate2": {
            "donors": 0,
            "receipts": 0,
            "amt": 0
        },
        "debate3": {
            "donors": 0,
            "receipts": 0,
            "amt": 0
        },
        "debate4": {
            "donors": 0,
            "receipts": 0,
            "amt": 0
        },
        "debate5": {
            "donors": 0,
            "receipts": 0,
            "amt": 0
        },
        "debate6": {
            "donors": 0,
            "receipts": 0,
            "amt": 0
        },
        "debate7": {
            "donors": 0,
            "receipts": 0,
            "amt": 0
        },
        "inState": {
            "donors": 0,
            "receipts": 0,
            "amt": 0
        },
        "outOfState": {
            "donors": 0,
            "receipts": 0,
            "amt": 0
        },
        "prior": {
            "donors": 0,
            "receipts": 0,
            "amt": 0
        },
        "loyal": {
            "donors": 0,
            "receipts": 0,
            "amt": 0
        },
        "donor2016": {
            "donors": 0,
            "receipts": 0,
            "amt": 0
        },
        "clinton2016": {
            "donors": 0,
            "receipts": 0,
            "amt": 0
        },
        "sanders2016": {
            "donors": 0,
            "receipts": 0,
            "amt": 0
        },
        "obama2012": {
            "donors": 0,
            "receipts": 0,
            "amt": 0
        },
        "traitor": {
            "donors": 0,
            "receipts": 0,
            "amt": 0
        },
        "elite": {
            "donors": 0,
            "receipts": 0,
            "amt": 0
        },
        "party": {
            "donors": 0,
            "receipts": 0,
            "amt": 0
        },
        "nationalParty": {
            "donors": 0,
            "receipts": 0,
            "amt": 0
        },
        "stateParty": {
            "donors": 0,
            "receipts": 0,
            "amt": 0
        },
        "localParty": {
            "donors": 0,
            "receipts": 0,
            "amt": 0
        },
        "competitorEndorsement": {
            "donors": 0,
            "receipts": 0,
            "amt": 0
        },
        "congressionalEndorsement": {
            "donors": 0,
            "receipts": 0,
            "amt": 0
        },
        "senateEndorsement": {
            "donors": 0,
            "receipts": 0,
            "amt": 0
        },
        "houseEndorsement": {
            "donors": 0,
            "receipts": 0,
            "amt": 0
        }
    },
    "competitorEndorsement": {
        "oneDollar": {
            "donors": 0,
            "receipts": 0,
            "amt": 0
        },
        "oneToTwoHundredDollars": {
            "donors": 0,
            "receipts": 0,
            "amt": 0
        },
        "twoHundredToOneThousandDollars": {
            "donors": 0,
            "receipts": 0,
            "amt": 0
        },
        "oneThousandToTwentyEightHundredDollars": {
            "donors": 0,
            "receipts": 0,
            "amt": 0
        },
        "twentyEightHundredDollars": {
            "donors": 0,
            "receipts": 0,
            "amt": 0
        },
        "full2020PrimaryCycle": {
            "donors": 0,
            "receipts": 0,
            "amt": 0
        },
        "pre2019": {
            "donors": 0,
            "receipts": 0,
            "amt": 0
        },
        "q12019": {
            "donors": 0,
            "receipts": 0,
            "amt": 0
        },
        "q22019": {
            "donors": 0,
            "receipts": 0,
            "amt": 0
        },
        "q32019": {
            "donors": 0,
            "receipts": 0,
            "amt": 0
        },
        "q42019": {
            "donors": 0,
            "receipts": 0,
            "amt": 0
        },
        "q12020": {
            "donors": 0,
            "receipts": 0,
            "amt": 0
        },
        "debate1": {
            "donors": 0,
            "receipts": 0,
            "amt": 0
        },
        "debate2": {
            "donors": 0,
            "receipts": 0,
            "amt": 0
        },
        "debate3": {
            "donors": 0,
            "receipts": 0,
            "amt": 0
        },
        "debate4": {
            "donors": 0,
            "receipts": 0,
            "amt": 0
        },
        "debate5": {
            "donors": 0,
            "receipts": 0,
            "amt": 0
        },
        "debate6": {
            "donors": 0,
            "receipts": 0,
            "amt": 0
        },
        "debate7": {
            "donors": 0,
            "receipts": 0,
            "amt": 0
        },
        "inState": {
            "donors": 0,
            "receipts": 0,
            "amt": 0
        },
        "outOfState": {
            "donors": 0,
            "receipts": 0,
            "amt": 0
        },
        "prior": {
            "donors": 0,
            "receipts": 0,
            "amt": 0
        },
        "loyal": {
            "donors": 0,
            "receipts": 0,
            "amt": 0
        },
        "donor2016": {
            "donors": 0,
            "receipts": 0,
            "amt": 0
        },
        "clinton2016": {
            "donors": 0,
            "receipts": 0,
            "amt": 0
        },
        "sanders2016": {
            "donors": 0,
            "receipts": 0,
            "amt": 0
        },
        "obama2012": {
            "donors": 0,
            "receipts": 0,
            "amt": 0
        },
        "traitor": {
            "donors": 0,
            "receipts": 0,
            "amt": 0
        },
        "elite": {
            "donors": 0,
            "receipts": 0,
            "amt": 0
        },
        "party": {
            "donors": 0,
            "receipts": 0,
            "amt": 0
        },
        "nationalParty": {
            "donors": 0,
            "receipts": 0,
            "amt": 0
        },
        "stateParty": {
            "donors": 0,
            "receipts": 0,
            "amt": 0
        },
        "localParty": {
            "donors": 0,
            "receipts": 0,
            "amt": 0
        },
        "competitorEndorsement": {
            "donors": 0,
            "receipts": 0,
            "amt": 0
        },
        "congressionalEndorsement": {
            "donors": 0,
            "receipts": 0,
            "amt": 0
        },
        "senateEndorsement": {
            "donors": 0,
            "receipts": 0,
            "amt": 0
        },
        "houseEndorsement": {
            "donors": 0,
            "receipts": 0,
            "amt": 0
        }
    },
    "nonEndorsement": {
        "oneDollar": {
            "donors": 2386,
            "receipts": 2386,
            "amt": 2386
        },
        "oneToTwoHundredDollars": {
            "donors": 7994,
            "receipts": 9291,
            "amt": 134509.91
        },
        "twoHundredToOneThousandDollars": {
            "donors": 151,
            "receipts": 271,
            "amt": 55366
        },
        "oneThousandToTwentyEightHundredDollars": {
            "donors": 193,
            "receipts": 198,
            "amt": 270654
        },
        "twentyEightHundredDollars": {
            "donors": 333,
            "receipts": 338,
            "amt": 935215
        },
        "full2020PrimaryCycle": {
            "donors": 11057,
            "receipts": 12484,
            "amt": 1398130.91
        },
        "pre2019": {
            "donors": 0,
            "receipts": 0,
            "amt": 0
        },
        "q12019": {
            "donors": 0,
            "receipts": 0,
            "amt": 0
        },
        "q22019": {
            "donors": 6590,
            "receipts": 6871,
            "amt": 1062256.84
        },
        "q32019": {
            "donors": 4855,
            "receipts": 5600,
            "amt": 330194.07
        },
        "q42019": {
            "donors": 5,
            "receipts": 6,
            "amt": 5610
        },
        "q12020": {
            "donors": 4,
            "receipts": 7,
            "amt": 70
        },
        "debate1": {
            "donors": 3821,
            "receipts": 3915,
            "amt": 252957.3
        },
        "debate2": {
            "donors": 3267,
            "receipts": 3384,
            "amt": 858873.11
        },
        "debate3": {
            "donors": 4134,
            "receipts": 4417,
            "amt": 137897.8
        },
        "debate4": {
            "donors": 702,
            "receipts": 755,
            "amt": 142722.7
        },
        "debate5": {
            "donors": 3,
            "receipts": 3,
            "amt": 5601
        },
        "debate6": {
            "donors": 1,
            "receipts": 1,
            "amt": 3
        },
        "debate7": {
            "donors": 2,
            "receipts": 2,
            "amt": 6
        },
        "inState": {
            "donors": 6489,
            "receipts": 7267,
            "amt": 1091110.78
        },
        "outOfState": {
            "donors": 4568,
            "receipts": 5217,
            "amt": 307020.13
        },
        "prior": {
            "donors": 64,
            "receipts": 112,
            "amt": 92855
        },
        "loyal": {
            "donors": 7125,
            "receipts": 7709,
            "amt": 1039185.69
        },
        "donor2016": {
            "donors": 1522,
            "receipts": 1968,
            "amt": 211864.98
        },
        "clinton2016": {
            "donors": 503,
            "receipts": 669,
            "amt": 184969.49
        },
        "sanders2016": {
            "donors": 1144,
            "receipts": 1486,
            "amt": 36876.49
        },
        "obama2012": {
            "donors": 120,
            "receipts": 171,
            "amt": 30278
        },
        "traitor": {
            "donors": 242,
            "receipts": 274,
            "amt": 43234
        },
        "elite": {
            "donors": 5095,
            "receipts": 6196,
            "amt": 1134715.66
        },
        "party": {
            "donors": 4426,
            "receipts": 5411,
            "amt": 444792.91
        },
        "nationalParty": {
            "donors": 4264,
            "receipts": 5223,
            "amt": 412468.91
        },
        "stateParty": {
            "donors": 1838,
            "receipts": 2434,
            "amt": 159466.64
        },
        "localParty": {
            "donors": 301,
            "receipts": 413,
            "amt": 34163.44
        },
        "competitorEndorsement": {
            "donors": 0,
            "receipts": 0,
            "amt": 0
        },
        "congressionalEndorsement": {
            "donors": 0,
            "receipts": 0,
            "amt": 0
        },
        "senateEndorsement": {
            "donors": 0,
            "receipts": 0,
            "amt": 0
        },
        "houseEndorsement": {
            "donors": 0,
            "receipts": 0,
            "amt": 0
        }
    },
    "unfaithful": {
        "oneDollar": {
            "donors": 984,
            "receipts": 984,
            "amt": 984
        },
        "oneToTwoHundredDollars": {
            "donors": 2738,
            "receipts": 3524,
            "amt": 48814.22
        },
        "twoHundredToOneThousandDollars": {
            "donors": 68,
            "receipts": 121,
            "amt": 24340
        },
        "oneThousandToTwentyEightHundredDollars": {
            "donors": 73,
            "receipts": 76,
            "amt": 91604
        },
        "twentyEightHundredDollars": {
            "donors": 69,
            "receipts": 70,
            "amt": 193203
        },
        "full2020PrimaryCycle": {
            "donors": 3932,
            "receipts": 4775,
            "amt": 358945.22
        },
        "pre2019": {
            "donors": 0,
            "receipts": 0,
            "amt": 0
        },
        "q12019": {
            "donors": 0,
            "receipts": 0,
            "amt": 0
        },
        "q22019": {
            "donors": 1468,
            "receipts": 1634,
            "amt": 274542.76
        },
        "q32019": {
            "donors": 2663,
            "receipts": 3133,
            "amt": 81579.46
        },
        "q42019": {
            "donors": 2,
            "receipts": 3,
            "amt": 2806
        },
        "q12020": {
            "donors": 2,
            "receipts": 5,
            "amt": 17
        },
        "debate1": {
            "donors": 712,
            "receipts": 767,
            "amt": 82918.55
        },
        "debate2": {
            "donors": 1021,
            "receipts": 1084,
            "amt": 209474.78
        },
        "debate3": {
            "donors": 2317,
            "receipts": 2520,
            "amt": 43432.19
        },
        "debate4": {
            "donors": 353,
            "receipts": 396,
            "amt": 20296.7
        },
        "debate5": {
            "donors": 1,
            "receipts": 1,
            "amt": 2800
        },
        "debate6": {
            "donors": 1,
            "receipts": 1,
            "amt": 3
        },
        "debate7": {
            "donors": 1,
            "receipts": 1,
            "amt": 3
        },
        "inState": {
            "donors": 1121,
            "receipts": 1456,
            "amt": 258078.39
        },
        "outOfState": {
            "donors": 2811,
            "receipts": 3319,
            "amt": 100866.83
        },
        "prior": {
            "donors": 37,
            "receipts": 70,
            "amt": 47603
        },
        "loyal": {
            "donors": 0,
            "receipts": 0,
            "amt": 0
        },
        "donor2016": {
            "donors": 1388,
            "receipts": 1789,
            "amt": 152931.78
        },
        "clinton2016": {
            "donors": 449,
            "receipts": 592,
            "amt": 137640.49
        },
        "sanders2016": {
            "donors": 1062,
            "receipts": 1382,
            "amt": 28034.29
        },
        "obama2012": {
            "donors": 109,
            "receipts": 151,
            "amt": 26350
        },
        "traitor": {
            "donors": 77,
            "receipts": 91,
            "amt": 10175
        },
        "elite": {
            "donors": 3489,
            "receipts": 4299,
            "amt": 346465.71
        },
        "party": {
            "donors": 3285,
            "receipts": 4071,
            "amt": 272903.71
        },
        "nationalParty": {
            "donors": 3209,
            "receipts": 3987,
            "amt": 256815.71
        },
        "stateParty": {
            "donors": 1669,
            "receipts": 2210,
            "amt": 118982.64
        },
        "localParty": {
            "donors": 280,
            "receipts": 392,
            "amt": 33682.44
        },
        "competitorEndorsement": {
            "donors": 0,
            "receipts": 0,
            "amt": 0
        },
        "congressionalEndorsement": {
            "donors": 0,
            "receipts": 0,
            "amt": 0
        },
        "senateEndorsement": {
            "donors": 0,
            "receipts": 0,
            "amt": 0
        },
        "houseEndorsement": {
            "donors": 0,
            "receipts": 0,
            "amt": 0
        }
    },
    "loyal": {
        "oneDollar": {
            "donors": 1402,
            "receipts": 1402,
            "amt": 1402
        },
        "oneToTwoHundredDollars": {
            "donors": 5256,
            "receipts": 5767,
            "amt": 85695.69
        },
        "twoHundredToOneThousandDollars": {
            "donors": 83,
            "receipts": 150,
            "amt": 31026
        },
        "oneThousandToTwentyEightHundredDollars": {
            "donors": 120,
            "receipts": 122,
            "amt": 179050
        },
        "twentyEightHundredDollars": {
            "donors": 264,
            "receipts": 268,
            "amt": 742012
        },
        "full2020PrimaryCycle": {
            "donors": 7125,
            "receipts": 7709,
            "amt": 1039185.69
        },
        "pre2019": {
            "donors": 0,
            "receipts": 0,
            "amt": 0
        },
        "q12019": {
            "donors": 0,
            "receipts": 0,
            "amt": 0
        },
        "q22019": {
            "donors": 5122,
            "receipts": 5237,
            "amt": 787714.08
        },
        "q32019": {
            "donors": 2192,
            "receipts": 2467,
            "amt": 248614.61
        },
        "q42019": {
            "donors": 3,
            "receipts": 3,
            "amt": 2804
        },
        "q12020": {
            "donors": 2,
            "receipts": 2,
            "amt": 53
        },
        "debate1": {
            "donors": 3109,
            "receipts": 3148,
            "amt": 170038.75
        },
        "debate2": {
            "donors": 2246,
            "receipts": 2300,
            "amt": 649398.33
        },
        "debate3": {
            "donors": 1817,
            "receipts": 1897,
            "amt": 94465.61
        },
        "debate4": {
            "donors": 349,
            "receipts": 359,
            "amt": 122426
        },
        "debate5": {
            "donors": 2,
            "receipts": 2,
            "amt": 2801
        },
        "debate6": {
            "donors": 0,
            "receipts": 0,
            "amt": 0
        },
        "debate7": {
            "donors": 1,
            "receipts": 1,
            "amt": 3
        },
        "inState": {
            "donors": 5368,
            "receipts": 5811,
            "amt": 833032.39
        },
        "outOfState": {
            "donors": 1757,
            "receipts": 1898,
            "amt": 206153.3
        },
        "prior": {
            "donors": 27,
            "receipts": 42,
            "amt": 45252
        },
        "loyal": {
            "donors": 7125,
            "receipts": 7709,
            "amt": 1039185.69
        },
        "donor2016": {
            "donors": 134,
            "receipts": 179,
            "amt": 58933.2
        },
        "clinton2016": {
            "donors": 54,
            "receipts": 77,
            "amt": 47329
        },
        "sanders2016": {
            "donors": 82,
            "receipts": 104,
            "amt": 8842.2
        },
        "obama2012": {
            "donors": 11,
            "receipts": 20,
            "amt": 3928
        },
        "traitor": {
            "donors": 165,
            "receipts": 183,
            "amt": 33059
        },
        "elite": {
            "donors": 1606,
            "receipts": 1897,
            "amt": 788249.95
        },
        "party": {
            "donors": 1141,
            "receipts": 1340,
            "amt": 171889.2
        },
        "nationalParty": {
            "donors": 1055,
            "receipts": 1236,
            "amt": 155653.2
        },
        "stateParty": {
            "donors": 169,
            "receipts": 224,
            "amt": 40484
        },
        "localParty": {
            "donors": 21,
            "receipts": 21,
            "amt": 481
        },
        "competitorEndorsement": {
            "donors": 0,
            "receipts": 0,
            "amt": 0
        },
        "congressionalEndorsement": {
            "donors": 0,
            "receipts": 0,
            "amt": 0
        },
        "senateEndorsement": {
            "donors": 0,
            "receipts": 0,
            "amt": 0
        },
        "houseEndorsement": {
            "donors": 0,
            "receipts": 0,
            "amt": 0
        }
    },
    "donor2016": {
        "oneDollar": {
            "donors": 313,
            "receipts": 313,
            "amt": 313
        },
        "oneToTwoHundredDollars": {
            "donors": 1092,
            "receipts": 1504,
            "amt": 21101.98
        },
        "twoHundredToOneThousandDollars": {
            "donors": 32,
            "receipts": 66,
            "amt": 12350
        },
        "oneThousandToTwentyEightHundredDollars": {
            "donors": 43,
            "receipts": 43,
            "amt": 60500
        },
        "twentyEightHundredDollars": {
            "donors": 42,
            "receipts": 42,
            "amt": 117600
        },
        "full2020PrimaryCycle": {
            "donors": 1522,
            "receipts": 1968,
            "amt": 211864.98
        },
        "pre2019": {
            "donors": 0,
            "receipts": 0,
            "amt": 0
        },
        "q12019": {
            "donors": 0,
            "receipts": 0,
            "amt": 0
        },
        "q22019": {
            "donors": 620,
            "receipts": 726,
            "amt": 169904.73
        },
        "q32019": {
            "donors": 995,
            "receipts": 1235,
            "amt": 39142.25
        },
        "q42019": {
            "donors": 2,
            "receipts": 3,
            "amt": 2806
        },
        "q12020": {
            "donors": 1,
            "receipts": 4,
            "amt": 12
        },
        "debate1": {
            "donors": 311,
            "receipts": 342,
            "amt": 45593.55
        },
        "debate2": {
            "donors": 431,
            "receipts": 460,
            "amt": 129688.75
        },
        "debate3": {
            "donors": 862,
            "receipts": 974,
            "amt": 14361.98
        },
        "debate4": {
            "donors": 158,
            "receipts": 185,
            "amt": 19402.7
        },
        "debate5": {
            "donors": 1,
            "receipts": 1,
            "amt": 2800
        },
        "debate6": {
            "donors": 1,
            "receipts": 1,
            "amt": 3
        },
        "debate7": {
            "donors": 1,
            "receipts": 1,
            "amt": 3
        },
        "inState": {
            "donors": 455,
            "receipts": 638,
            "amt": 155958.43
        },
        "outOfState": {
            "donors": 1067,
            "receipts": 1330,
            "amt": 55906.55
        },
        "prior": {
            "donors": 21,
            "receipts": 48,
            "amt": 29614
        },
        "loyal": {
            "donors": 134,
            "receipts": 179,
            "amt": 58933.2
        },
        "donor2016": {
            "donors": 1522,
            "receipts": 1968,
            "amt": 211864.98
        },
        "clinton2016": {
            "donors": 503,
            "receipts": 669,
            "amt": 184969.49
        },
        "sanders2016": {
            "donors": 1144,
            "receipts": 1486,
            "amt": 36876.49
        },
        "obama2012": {
            "donors": 73,
            "receipts": 102,
            "amt": 16053
        },
        "traitor": {
            "donors": 21,
            "receipts": 28,
            "amt": 6986
        },
        "elite": {
            "donors": 1479,
            "receipts": 1919,
            "amt": 200400.98
        },
        "party": {
            "donors": 1442,
            "receipts": 1882,
            "amt": 172956.98
        },
        "nationalParty": {
            "donors": 1425,
            "receipts": 1861,
            "amt": 167946.98
        },
        "stateParty": {
            "donors": 901,
            "receipts": 1236,
            "amt": 83103.97
        },
        "localParty": {
            "donors": 165,
            "receipts": 236,
            "amt": 15211.94
        },
        "competitorEndorsement": {
            "donors": 0,
            "receipts": 0,
            "amt": 0
        },
        "congressionalEndorsement": {
            "donors": 0,
            "receipts": 0,
            "amt": 0
        },
        "senateEndorsement": {
            "donors": 0,
            "receipts": 0,
            "amt": 0
        },
        "houseEndorsement": {
            "donors": 0,
            "receipts": 0,
            "amt": 0
        }
    },
    "clinton2016": {
        "oneDollar": {
            "donors": 58,
            "receipts": 58,
            "amt": 58
        },
        "oneToTwoHundredDollars": {
            "donors": 338,
            "receipts": 485,
            "amt": 9286.49
        },
        "twoHundredToOneThousandDollars": {
            "donors": 29,
            "receipts": 48,
            "amt": 10925
        },
        "oneThousandToTwentyEightHundredDollars": {
            "donors": 39,
            "receipts": 39,
            "amt": 55500
        },
        "twentyEightHundredDollars": {
            "donors": 39,
            "receipts": 39,
            "amt": 109200
        },
        "full2020PrimaryCycle": {
            "donors": 503,
            "receipts": 669,
            "amt": 184969.49
        },
        "pre2019": {
            "donors": 0,
            "receipts": 0,
            "amt": 0
        },
        "q12019": {
            "donors": 0,
            "receipts": 0,
            "amt": 0
        },
        "q22019": {
            "donors": 246,
            "receipts": 290,
            "amt": 155183.92
        },
        "q32019": {
            "donors": 291,
            "receipts": 379,
            "amt": 29785.57
        },
        "q42019": {
            "donors": 0,
            "receipts": 0,
            "amt": 0
        },
        "q12020": {
            "donors": 0,
            "receipts": 0,
            "amt": 0
        },
        "debate1": {
            "donors": 117,
            "receipts": 132,
            "amt": 41499.55
        },
        "debate2": {
            "donors": 179,
            "receipts": 191,
            "amt": 118425.94
        },
        "debate3": {
            "donors": 234,
            "receipts": 273,
            "amt": 8588
        },
        "debate4": {
            "donors": 65,
            "receipts": 73,
            "amt": 16456
        },
        "debate5": {
            "donors": 0,
            "receipts": 0,
            "amt": 0
        },
        "debate6": {
            "donors": 0,
            "receipts": 0,
            "amt": 0
        },
        "debate7": {
            "donors": 0,
            "receipts": 0,
            "amt": 0
        },
        "inState": {
            "donors": 224,
            "receipts": 317,
            "amt": 140614.55
        },
        "outOfState": {
            "donors": 279,
            "receipts": 352,
            "amt": 44354.94
        },
        "prior": {
            "donors": 15,
            "receipts": 23,
            "amt": 28333
        },
        "loyal": {
            "donors": 54,
            "receipts": 77,
            "amt": 47329
        },
        "donor2016": {
            "donors": 503,
            "receipts": 669,
            "amt": 184969.49
        },
        "clinton2016": {
            "donors": 503,
            "receipts": 669,
            "amt": 184969.49
        },
        "sanders2016": {
            "donors": 130,
            "receipts": 192,
            "amt": 12787
        },
        "obama2012": {
            "donors": 52,
            "receipts": 67,
            "amt": 15651
        },
        "traitor": {
            "donors": 7,
            "receipts": 9,
            "amt": 5833
        },
        "elite": {
            "donors": 493,
            "receipts": 653,
            "amt": 173980.49
        },
        "party": {
            "donors": 474,
            "receipts": 634,
            "amt": 149527.49
        },
        "nationalParty": {
            "donors": 467,
            "receipts": 624,
            "amt": 144615.49
        },
        "stateParty": {
            "donors": 335,
            "receipts": 459,
            "amt": 69187.49
        },
        "localParty": {
            "donors": 90,
            "receipts": 130,
            "amt": 14107.94
        },
        "competitorEndorsement": {
            "donors": 0,
            "receipts": 0,
            "amt": 0
        },
        "congressionalEndorsement": {
            "donors": 0,
            "receipts": 0,
            "amt": 0
        },
        "senateEndorsement": {
            "donors": 0,
            "receipts": 0,
            "amt": 0
        },
        "houseEndorsement": {
            "donors": 0,
            "receipts": 0,
            "amt": 0
        }
    },
    "sanders2016": {
        "oneDollar": {
            "donors": 263,
            "receipts": 263,
            "amt": 263
        },
        "oneToTwoHundredDollars": {
            "donors": 867,
            "receipts": 1194,
            "amt": 14988.49
        },
        "twoHundredToOneThousandDollars": {
            "donors": 4,
            "receipts": 19,
            "amt": 1925
        },
        "oneThousandToTwentyEightHundredDollars": {
            "donors": 6,
            "receipts": 6,
            "amt": 8500
        },
        "twentyEightHundredDollars": {
            "donors": 4,
            "receipts": 4,
            "amt": 11200
        },
        "full2020PrimaryCycle": {
            "donors": 1144,
            "receipts": 1486,
            "amt": 36876.49
        },
        "pre2019": {
            "donors": 0,
            "receipts": 0,
            "amt": 0
        },
        "q12019": {
            "donors": 0,
            "receipts": 0,
            "amt": 0
        },
        "q22019": {
            "donors": 434,
            "receipts": 507,
            "amt": 25948.81
        },
        "q32019": {
            "donors": 783,
            "receipts": 973,
            "amt": 10909.68
        },
        "q42019": {
            "donors": 1,
            "receipts": 2,
            "amt": 6
        },
        "q12020": {
            "donors": 1,
            "receipts": 4,
            "amt": 12
        },
        "debate1": {
            "donors": 227,
            "receipts": 246,
            "amt": 7684
        },
        "debate2": {
            "donors": 291,
            "receipts": 311,
            "amt": 18988.81
        },
        "debate3": {
            "donors": 696,
            "receipts": 787,
            "amt": 6978.98
        },
        "debate4": {
            "donors": 114,
            "receipts": 136,
            "amt": 3206.7
        },
        "debate5": {
            "donors": 0,
            "receipts": 0,
            "amt": 0
        },
        "debate6": {
            "donors": 1,
            "receipts": 1,
            "amt": 3
        },
        "debate7": {
            "donors": 1,
            "receipts": 1,
            "amt": 3
        },
        "inState": {
            "donors": 269,
            "receipts": 384,
            "amt": 26153.88
        },
        "outOfState": {
            "donors": 875,
            "receipts": 1102,
            "amt": 10722.61
        },
        "prior": {
            "donors": 7,
            "receipts": 32,
            "amt": 1358
        },
        "loyal": {
            "donors": 82,
            "receipts": 104,
            "amt": 8842.2
        },
        "donor2016": {
            "donors": 1144,
            "receipts": 1486,
            "amt": 36876.49
        },
        "clinton2016": {
            "donors": 130,
            "receipts": 192,
            "amt": 12787
        },
        "sanders2016": {
            "donors": 1144,
            "receipts": 1486,
            "amt": 36876.49
        },
        "obama2012": {
            "donors": 34,
            "receipts": 56,
            "amt": 927
        },
        "traitor": {
            "donors": 15,
            "receipts": 20,
            "amt": 1163
        },
        "elite": {
            "donors": 1110,
            "receipts": 1452,
            "amt": 36398.49
        },
        "party": {
            "donors": 1092,
            "receipts": 1434,
            "amt": 33407.49
        },
        "nationalParty": {
            "donors": 1082,
            "receipts": 1423,
            "amt": 33309.49
        },
        "stateParty": {
            "donors": 675,
            "receipts": 946,
            "amt": 17806.48
        },
        "localParty": {
            "donors": 112,
            "receipts": 167,
            "amt": 2369
        },
        "competitorEndorsement": {
            "donors": 0,
            "receipts": 0,
            "amt": 0
        },
        "congressionalEndorsement": {
            "donors": 0,
            "receipts": 0,
            "amt": 0
        },
        "senateEndorsement": {
            "donors": 0,
            "receipts": 0,
            "amt": 0
        },
        "houseEndorsement": {
            "donors": 0,
            "receipts": 0,
            "amt": 0
        }
    },
    "elite": {
        "oneDollar": {
            "donors": 1081,
            "receipts": 1081,
            "amt": 1081
        },
        "oneToTwoHundredDollars": {
            "donors": 3434,
            "receipts": 4411,
            "amt": 63771.66
        },
        "twoHundredToOneThousandDollars": {
            "donors": 137,
            "receipts": 251,
            "amt": 50294
        },
        "oneThousandToTwentyEightHundredDollars": {
            "donors": 154,
            "receipts": 159,
            "amt": 207554
        },
        "twentyEightHundredDollars": {
            "donors": 289,
            "receipts": 294,
            "amt": 812015
        },
        "full2020PrimaryCycle": {
            "donors": 5095,
            "receipts": 6196,
            "amt": 1134715.66
        },
        "pre2019": {
            "donors": 0,
            "receipts": 0,
            "amt": 0
        },
        "q12019": {
            "donors": 0,
            "receipts": 0,
            "amt": 0
        },
        "q22019": {
            "donors": 2411,
            "receipts": 2635,
            "amt": 865044
        },
        "q32019": {
            "donors": 2977,
            "receipts": 3549,
            "amt": 263994.66
        },
        "q42019": {
            "donors": 5,
            "receipts": 6,
            "amt": 5610
        },
        "q12020": {
            "donors": 3,
            "receipts": 6,
            "amt": 67
        },
        "debate1": {
            "donors": 1181,
            "receipts": 1254,
            "amt": 199702.3
        },
        "debate2": {
            "donors": 1578,
            "receipts": 1667,
            "amt": 706079.27
        },
        "debate3": {
            "donors": 2508,
            "receipts": 2741,
            "amt": 109344.39
        },
        "debate4": {
            "donors": 471,
            "receipts": 522,
            "amt": 113912.7
        },
        "debate5": {
            "donors": 3,
            "receipts": 3,
            "amt": 5601
        },
        "debate6": {
            "donors": 1,
            "receipts": 1,
            "amt": 3
        },
        "debate7": {
            "donors": 2,
            "receipts": 2,
            "amt": 6
        },
        "inState": {
            "donors": 2144,
            "receipts": 2668,
            "amt": 884220.93
        },
        "outOfState": {
            "donors": 2951,
            "receipts": 3528,
            "amt": 250494.73
        },
        "prior": {
            "donors": 64,
            "receipts": 112,
            "amt": 92855
        },
        "loyal": {
            "donors": 1606,
            "receipts": 1897,
            "amt": 788249.95
        },
        "donor2016": {
            "donors": 1479,
            "receipts": 1919,
            "amt": 200400.98
        },
        "clinton2016": {
            "donors": 493,
            "receipts": 653,
            "amt": 173980.49
        },
        "sanders2016": {
            "donors": 1110,
            "receipts": 1452,
            "amt": 36398.49
        },
        "obama2012": {
            "donors": 118,
            "receipts": 169,
            "amt": 30225
        },
        "traitor": {
            "donors": 210,
            "receipts": 239,
            "amt": 43060
        },
        "elite": {
            "donors": 5095,
            "receipts": 6196,
            "amt": 1134715.66
        },
        "party": {
            "donors": 4426,
            "receipts": 5411,
            "amt": 444792.91
        },
        "nationalParty": {
            "donors": 4264,
            "receipts": 5223,
            "amt": 412468.91
        },
        "stateParty": {
            "donors": 1838,
            "receipts": 2434,
            "amt": 159466.64
        },
        "localParty": {
            "donors": 301,
            "receipts": 413,
            "amt": 34163.44
        },
        "competitorEndorsement": {
            "donors": 0,
            "receipts": 0,
            "amt": 0
        },
        "congressionalEndorsement": {
            "donors": 0,
            "receipts": 0,
            "amt": 0
        },
        "senateEndorsement": {
            "donors": 0,
            "receipts": 0,
            "amt": 0
        },
        "houseEndorsement": {
            "donors": 0,
            "receipts": 0,
            "amt": 0
        }
    },
    "eliteParty": {
        "oneDollar": {
            "donors": 1013,
            "receipts": 1013,
            "amt": 1013
        },
        "oneToTwoHundredDollars": {
            "donors": 3173,
            "receipts": 4076,
            "amt": 58257.91
        },
        "twoHundredToOneThousandDollars": {
            "donors": 67,
            "receipts": 145,
            "amt": 24566
        },
        "oneThousandToTwentyEightHundredDollars": {
            "donors": 82,
            "receipts": 85,
            "amt": 106153
        },
        "twentyEightHundredDollars": {
            "donors": 91,
            "receipts": 92,
            "amt": 254803
        },
        "full2020PrimaryCycle": {
            "donors": 4426,
            "receipts": 5411,
            "amt": 444792.91
        },
        "pre2019": {
            "donors": 0,
            "receipts": 0,
            "amt": 0
        },
        "q12019": {
            "donors": 0,
            "receipts": 0,
            "amt": 0
        },
        "q22019": {
            "donors": 1997,
            "receipts": 2202,
            "amt": 352877.25
        },
        "q32019": {
            "donors": 2668,
            "receipts": 3198,
            "amt": 89038.66
        },
        "q42019": {
            "donors": 4,
            "receipts": 5,
            "amt": 2810
        },
        "q12020": {
            "donors": 3,
            "receipts": 6,
            "amt": 67
        },
        "debate1": {
            "donors": 1012,
            "receipts": 1077,
            "amt": 103262.55
        },
        "debate2": {
            "donors": 1266,
            "receipts": 1346,
            "amt": 261873.27
        },
        "debate3": {
            "donors": 2309,
            "receipts": 2530,
            "amt": 49453.39
        },
        "debate4": {
            "donors": 402,
            "receipts": 447,
            "amt": 27326.7
        },
        "debate5": {
            "donors": 2,
            "receipts": 2,
            "amt": 2801
        },
        "debate6": {
            "donors": 1,
            "receipts": 1,
            "amt": 3
        },
        "debate7": {
            "donors": 2,
            "receipts": 2,
            "amt": 6
        },
        "inState": {
            "donors": 1718,
            "receipts": 2154,
            "amt": 341344.18
        },
        "outOfState": {
            "donors": 2708,
            "receipts": 3257,
            "amt": 103448.73
        },
        "prior": {
            "donors": 46,
            "receipts": 87,
            "amt": 48603
        },
        "loyal": {
            "donors": 1141,
            "receipts": 1340,
            "amt": 171889.2
        },
        "donor2016": {
            "donors": 1442,
            "receipts": 1882,
            "amt": 172956.98
        },
        "clinton2016": {
            "donors": 474,
            "receipts": 634,
            "amt": 149527.49
        },
        "sanders2016": {
            "donors": 1092,
            "receipts": 1434,
            "amt": 33407.49
        },
        "obama2012": {
            "donors": 115,
            "receipts": 166,
            "amt": 30173
        },
        "traitor": {
            "donors": 202,
            "receipts": 231,
            "amt": 37418
        },
        "elite": {
            "donors": 4426,
            "receipts": 5411,
            "amt": 444792.91
        },
        "party": {
            "donors": 4426,
            "receipts": 5411,
            "amt": 444792.91
        },
        "nationalParty": {
            "donors": 4264,
            "receipts": 5223,
            "amt": 412468.91
        },
        "stateParty": {
            "donors": 1838,
            "receipts": 2434,
            "amt": 159466.64
        },
        "localParty": {
            "donors": 301,
            "receipts": 413,
            "amt": 34163.44
        },
        "competitorEndorsement": {
            "donors": 0,
            "receipts": 0,
            "amt": 0
        },
        "congressionalEndorsement": {
            "donors": 0,
            "receipts": 0,
            "amt": 0
        },
        "senateEndorsement": {
            "donors": 0,
            "receipts": 0,
            "amt": 0
        },
        "houseEndorsement": {
            "donors": 0,
            "receipts": 0,
            "amt": 0
        }
    },
    "elitePac": {
        "oneDollar": {
            "donors": 698,
            "receipts": 698,
            "amt": 698
        },
        "oneToTwoHundredDollars": {
            "donors": 2412,
            "receipts": 3212,
            "amt": 46992.91
        },
        "twoHundredToOneThousandDollars": {
            "donors": 135,
            "receipts": 248,
            "amt": 49594
        },
        "oneThousandToTwentyEightHundredDollars": {
            "donors": 149,
            "receipts": 154,
            "amt": 200054
        },
        "twentyEightHundredDollars": {
            "donors": 283,
            "receipts": 288,
            "amt": 795215
        },
        "full2020PrimaryCycle": {
            "donors": 3677,
            "receipts": 4600,
            "amt": 1092553.91
        },
        "pre2019": {
            "donors": 0,
            "receipts": 0,
            "amt": 0
        },
        "q12019": {
            "donors": 0,
            "receipts": 0,
            "amt": 0
        },
        "q22019": {
            "donors": 1585,
            "receipts": 1772,
            "amt": 836750.25
        },
        "q32019": {
            "donors": 2330,
            "receipts": 2818,
            "amt": 250130.66
        },
        "q42019": {
            "donors": 3,
            "receipts": 4,
            "amt": 5606
        },
        "q12020": {
            "donors": 3,
            "receipts": 6,
            "amt": 67
        },
        "debate1": {
            "donors": 763,
            "receipts": 823,
            "amt": 187220.3
        },
        "debate2": {
            "donors": 1114,
            "receipts": 1187,
            "amt": 688770.52
        },
        "debate3": {
            "donors": 1952,
            "receipts": 2159,
            "amt": 105232.39
        },
        "debate4": {
            "donors": 371,
            "receipts": 421,
            "amt": 105657.7
        },
        "debate5": {
            "donors": 2,
            "receipts": 2,
            "amt": 5600
        },
        "debate6": {
            "donors": 1,
            "receipts": 1,
            "amt": 3
        },
        "debate7": {
            "donors": 1,
            "receipts": 1,
            "amt": 3
        },
        "inState": {
            "donors": 1373,
            "receipts": 1790,
            "amt": 848521.18
        },
        "outOfState": {
            "donors": 2304,
            "receipts": 2810,
            "amt": 244032.73
        },
        "prior": {
            "donors": 64,
            "receipts": 112,
            "amt": 92855
        },
        "loyal": {
            "donors": 811,
            "receipts": 1000,
            "amt": 759180.95
        },
        "donor2016": {
            "donors": 1338,
            "receipts": 1746,
            "amt": 191411.98
        },
        "clinton2016": {
            "donors": 478,
            "receipts": 632,
            "amt": 168002.49
        },
        "sanders2016": {
            "donors": 983,
            "receipts": 1298,
            "amt": 33343.49
        },
        "obama2012": {
            "donors": 114,
            "receipts": 164,
            "amt": 30039
        },
        "traitor": {
            "donors": 114,
            "receipts": 141,
            "amt": 39645
        },
        "elite": {
            "donors": 3677,
            "receipts": 4600,
            "amt": 1092553.91
        },
        "party": {
            "donors": 3008,
            "receipts": 3815,
            "amt": 402631.16
        },
        "nationalParty": {
            "donors": 2943,
            "receipts": 3736,
            "amt": 371533.16
        },
        "stateParty": {
            "donors": 1654,
            "receipts": 2219,
            "amt": 152619.64
        },
        "localParty": {
            "donors": 284,
            "receipts": 394,
            "amt": 34130.44
        },
        "competitorEndorsement": {
            "donors": 0,
            "receipts": 0,
            "amt": 0
        },
        "congressionalEndorsement": {
            "donors": 0,
            "receipts": 0,
            "amt": 0
        },
        "senateEndorsement": {
            "donors": 0,
            "receipts": 0,
            "amt": 0
        },
        "houseEndorsement": {
            "donors": 0,
            "receipts": 0,
            "amt": 0
        }
    }
}