{
    "all": {
        "oneDollar": {
            "donors": 2652,
            "receipts": 2652,
            "amt": 2652
        },
        "oneToTwoHundredDollars": {
            "donors": 11428,
            "receipts": 15576,
            "amt": 292597.31
        },
        "twoHundredToOneThousandDollars": {
            "donors": 556,
            "receipts": 1637,
            "amt": 208484.8
        },
        "oneThousandToTwentyEightHundredDollars": {
            "donors": 211,
            "receipts": 457,
            "amt": 279259
        },
        "twentyEightHundredDollars": {
            "donors": 227,
            "receipts": 343,
            "amt": 716115.4
        },
        "full2020PrimaryCycle": {
            "donors": 15074,
            "receipts": 20665,
            "amt": 1499108.51
        },
        "pre2019": {
            "donors": 27,
            "receipts": 38,
            "amt": 19378
        },
        "q12019": {
            "donors": 122,
            "receipts": 157,
            "amt": 163385
        },
        "q22019": {
            "donors": 13822,
            "receipts": 17369,
            "amt": 1092642.05
        },
        "q32019": {
            "donors": 2167,
            "receipts": 3096,
            "amt": 221678.26
        },
        "q42019": {
            "donors": 2,
            "receipts": 2,
            "amt": 1000
        },
        "q12020": {
            "donors": 2,
            "receipts": 2,
            "amt": 1005
        },
        "debate1": {
            "donors": 12797,
            "receipts": 15033,
            "amt": 1005100.26
        },
        "debate2": {
            "donors": 2724,
            "receipts": 3546,
            "amt": 310349.37
        },
        "debate3": {
            "donors": 1520,
            "receipts": 2023,
            "amt": 153375.68
        },
        "debate4": {
            "donors": 20,
            "receipts": 20,
            "amt": 8880
        },
        "debate5": {
            "donors": 2,
            "receipts": 2,
            "amt": 1000
        },
        "debate6": {
            "donors": 0,
            "receipts": 0,
            "amt": 0
        },
        "debate7": {
            "donors": 0,
            "receipts": 0,
            "amt": 0
        },
        "inState": {
            "donors": 4403,
            "receipts": 6241,
            "amt": 611473.98
        },
        "outOfState": {
            "donors": 10671,
            "receipts": 14424,
            "amt": 887634.53
        },
        "prior": {
            "donors": 1521,
            "receipts": 2842,
            "amt": 793435.35
        },
        "loyal": {
            "donors": 4542,
            "receipts": 5538,
            "amt": 678628.55
        },
        "donor2016": {
            "donors": 3448,
            "receipts": 5203,
            "amt": 270842.12
        },
        "clinton2016": {
            "donors": 1456,
            "receipts": 2288,
            "amt": 194444.2
        },
        "sanders2016": {
            "donors": 2353,
            "receipts": 3458,
            "amt": 76317.57
        },
        "obama2012": {
            "donors": 477,
            "receipts": 708,
            "amt": 116630.98
        },
        "traitor": {
            "donors": 111,
            "receipts": 146,
            "amt": 10537
        },
        "elite": {
            "donors": 11557,
            "receipts": 16772,
            "amt": 1390179.88
        },
        "party": {
            "donors": 10317,
            "receipts": 15249,
            "amt": 958218.74
        },
        "nationalParty": {
            "donors": 10013,
            "receipts": 14900,
            "amt": 893242.71
        },
        "stateParty": {
            "donors": 5292,
            "receipts": 8419,
            "amt": 474014.04
        },
        "localParty": {
            "donors": 847,
            "receipts": 1567,
            "amt": 138034.44
        },
        "competitorEndorsement": {
            "donors": 0,
            "receipts": 0,
            "amt": 0
        },
        "congressionalEndorsement": {
            "donors": 0,
            "receipts": 0,
            "amt": 0
        },
        "senateEndorsement": {
            "donors": 0,
            "receipts": 0,
            "amt": 0
        },
        "houseEndorsement": {
            "donors": 0,
            "receipts": 0,
            "amt": 0
        }
    },
    "dayOneLaunch": {
        "oneDollar": {
            "donors": 59,
            "receipts": 59,
            "amt": 59
        },
        "oneToTwoHundredDollars": {
            "donors": 291,
            "receipts": 436,
            "amt": 7536.7
        },
        "twoHundredToOneThousandDollars": {
            "donors": 11,
            "receipts": 103,
            "amt": 3853.4
        },
        "oneThousandToTwentyEightHundredDollars": {
            "donors": 1,
            "receipts": 1,
            "amt": 1000
        },
        "twentyEightHundredDollars": {
            "donors": 0,
            "receipts": 0,
            "amt": 0
        },
        "full2020PrimaryCycle": {
            "donors": 362,
            "receipts": 599,
            "amt": 12449.1
        },
        "pre2019": {
            "donors": 3,
            "receipts": 7,
            "amt": 170
        },
        "q12019": {
            "donors": 2,
            "receipts": 9,
            "amt": 185
        },
        "q22019": {
            "donors": 362,
            "receipts": 528,
            "amt": 11130.8
        },
        "q32019": {
            "donors": 22,
            "receipts": 55,
            "amt": 963.3
        },
        "q42019": {
            "donors": 0,
            "receipts": 0,
            "amt": 0
        },
        "q12020": {
            "donors": 0,
            "receipts": 0,
            "amt": 0
        },
        "debate1": {
            "donors": 362,
            "receipts": 498,
            "amt": 10809.6
        },
        "debate2": {
            "donors": 28,
            "receipts": 57,
            "amt": 855.5
        },
        "debate3": {
            "donors": 16,
            "receipts": 36,
            "amt": 514
        },
        "debate4": {
            "donors": 1,
            "receipts": 1,
            "amt": 100
        },
        "debate5": {
            "donors": 0,
            "receipts": 0,
            "amt": 0
        },
        "debate6": {
            "donors": 0,
            "receipts": 0,
            "amt": 0
        },
        "debate7": {
            "donors": 0,
            "receipts": 0,
            "amt": 0
        },
        "inState": {
            "donors": 68,
            "receipts": 133,
            "amt": 4248.8
        },
        "outOfState": {
            "donors": 294,
            "receipts": 466,
            "amt": 8200.3
        },
        "prior": {
            "donors": 37,
            "receipts": 135,
            "amt": 4484.2
        },
        "loyal": {
            "donors": 99,
            "receipts": 135,
            "amt": 2411.6
        },
        "donor2016": {
            "donors": 73,
            "receipts": 125,
            "amt": 3180.8
        },
        "clinton2016": {
            "donors": 31,
            "receipts": 56,
            "amt": 1659.4
        },
        "sanders2016": {
            "donors": 48,
            "receipts": 80,
            "amt": 1673
        },
        "obama2012": {
            "donors": 10,
            "receipts": 19,
            "amt": 702.2
        },
        "traitor": {
            "donors": 1,
            "receipts": 1,
            "amt": 10
        },
        "elite": {
            "donors": 287,
            "receipts": 516,
            "amt": 11468.3
        },
        "party": {
            "donors": 257,
            "receipts": 480,
            "amt": 10684.3
        },
        "nationalParty": {
            "donors": 251,
            "receipts": 473,
            "amt": 10533.3
        },
        "stateParty": {
            "donors": 103,
            "receipts": 266,
            "amt": 5557.2
        },
        "localParty": {
            "donors": 20,
            "receipts": 42,
            "amt": 1259
        },
        "competitorEndorsement": {
            "donors": 0,
            "receipts": 0,
            "amt": 0
        },
        "congressionalEndorsement": {
            "donors": 0,
            "receipts": 0,
            "amt": 0
        },
        "senateEndorsement": {
            "donors": 0,
            "receipts": 0,
            "amt": 0
        },
        "houseEndorsement": {
            "donors": 0,
            "receipts": 0,
            "amt": 0
        }
    },
    "weekOneLaunch": {
        "oneDollar": {
            "donors": 362,
            "receipts": 362,
            "amt": 362
        },
        "oneToTwoHundredDollars": {
            "donors": 1409,
            "receipts": 2056,
            "amt": 42279.95
        },
        "twoHundredToOneThousandDollars": {
            "donors": 88,
            "receipts": 429,
            "amt": 33774.5
        },
        "oneThousandToTwentyEightHundredDollars": {
            "donors": 24,
            "receipts": 108,
            "amt": 33287.4
        },
        "twentyEightHundredDollars": {
            "donors": 15,
            "receipts": 24,
            "amt": 50450
        },
        "full2020PrimaryCycle": {
            "donors": 1898,
            "receipts": 2979,
            "amt": 160153.85
        },
        "pre2019": {
            "donors": 4,
            "receipts": 8,
            "amt": 420
        },
        "q12019": {
            "donors": 12,
            "receipts": 21,
            "amt": 3685
        },
        "q22019": {
            "donors": 1898,
            "receipts": 2680,
            "amt": 142144.45
        },
        "q32019": {
            "donors": 123,
            "receipts": 270,
            "amt": 13904.4
        },
        "q42019": {
            "donors": 0,
            "receipts": 0,
            "amt": 0
        },
        "q12020": {
            "donors": 0,
            "receipts": 0,
            "amt": 0
        },
        "debate1": {
            "donors": 1898,
            "receipts": 2496,
            "amt": 122475.05
        },
        "debate2": {
            "donors": 166,
            "receipts": 288,
            "amt": 27714.6
        },
        "debate3": {
            "donors": 97,
            "receipts": 184,
            "amt": 9324.2
        },
        "debate4": {
            "donors": 3,
            "receipts": 3,
            "amt": 220
        },
        "debate5": {
            "donors": 0,
            "receipts": 0,
            "amt": 0
        },
        "debate6": {
            "donors": 0,
            "receipts": 0,
            "amt": 0
        },
        "debate7": {
            "donors": 0,
            "receipts": 0,
            "amt": 0
        },
        "inState": {
            "donors": 499,
            "receipts": 915,
            "amt": 63773.95
        },
        "outOfState": {
            "donors": 1399,
            "receipts": 2064,
            "amt": 96379.9
        },
        "prior": {
            "donors": 253,
            "receipts": 684,
            "amt": 77497.75
        },
        "loyal": {
            "donors": 769,
            "receipts": 973,
            "amt": 72849.9
        },
        "donor2016": {
            "donors": 293,
            "receipts": 601,
            "amt": 32979.15
        },
        "clinton2016": {
            "donors": 126,
            "receipts": 304,
            "amt": 20550.5
        },
        "sanders2016": {
            "donors": 178,
            "receipts": 320,
            "amt": 8037.15
        },
        "obama2012": {
            "donors": 52,
            "receipts": 94,
            "amt": 12097.6
        },
        "traitor": {
            "donors": 9,
            "receipts": 11,
            "amt": 826
        },
        "elite": {
            "donors": 1314,
            "receipts": 2323,
            "amt": 145911.15
        },
        "party": {
            "donors": 1121,
            "receipts": 2084,
            "amt": 106568.35
        },
        "nationalParty": {
            "donors": 1077,
            "receipts": 2031,
            "amt": 100984.75
        },
        "stateParty": {
            "donors": 492,
            "receipts": 1099,
            "amt": 64048.5
        },
        "localParty": {
            "donors": 70,
            "receipts": 163,
            "amt": 17187.7
        },
        "competitorEndorsement": {
            "donors": 0,
            "receipts": 0,
            "amt": 0
        },
        "congressionalEndorsement": {
            "donors": 0,
            "receipts": 0,
            "amt": 0
        },
        "senateEndorsement": {
            "donors": 0,
            "receipts": 0,
            "amt": 0
        },
        "houseEndorsement": {
            "donors": 0,
            "receipts": 0,
            "amt": 0
        }
    },
    "firstTime": {
        "oneDollar": {
            "donors": 643,
            "receipts": 643,
            "amt": 643
        },
        "oneToTwoHundredDollars": {
            "donors": 1675,
            "receipts": 1887,
            "amt": 43709.47
        },
        "twoHundredToOneThousandDollars": {
            "donors": 13,
            "receipts": 20,
            "amt": 4250
        },
        "oneThousandToTwentyEightHundredDollars": {
            "donors": 8,
            "receipts": 8,
            "amt": 9700
        },
        "twentyEightHundredDollars": {
            "donors": 1,
            "receipts": 3,
            "amt": 2840.2
        },
        "full2020PrimaryCycle": {
            "donors": 2340,
            "receipts": 2561,
            "amt": 61142.67
        },
        "pre2019": {
            "donors": 0,
            "receipts": 0,
            "amt": 0
        },
        "q12019": {
            "donors": 0,
            "receipts": 0,
            "amt": 0
        },
        "q22019": {
            "donors": 2214,
            "receipts": 2368,
            "amt": 54452.97
        },
        "q32019": {
            "donors": 172,
            "receipts": 193,
            "amt": 6689.7
        },
        "q42019": {
            "donors": 0,
            "receipts": 0,
            "amt": 0
        },
        "q12020": {
            "donors": 0,
            "receipts": 0,
            "amt": 0
        },
        "debate1": {
            "donors": 2131,
            "receipts": 2225,
            "amt": 47466.17
        },
        "debate2": {
            "donors": 185,
            "receipts": 209,
            "amt": 8398.8
        },
        "debate3": {
            "donors": 120,
            "receipts": 126,
            "amt": 5027.7
        },
        "debate4": {
            "donors": 1,
            "receipts": 1,
            "amt": 250
        },
        "debate5": {
            "donors": 0,
            "receipts": 0,
            "amt": 0
        },
        "debate6": {
            "donors": 0,
            "receipts": 0,
            "amt": 0
        },
        "debate7": {
            "donors": 0,
            "receipts": 0,
            "amt": 0
        },
        "inState": {
            "donors": 784,
            "receipts": 854,
            "amt": 24605.6
        },
        "outOfState": {
            "donors": 1556,
            "receipts": 1707,
            "amt": 36537.07
        },
        "prior": {
            "donors": 0,
            "receipts": 0,
            "amt": 0
        },
        "loyal": {
            "donors": 2340,
            "receipts": 2561,
            "amt": 61142.67
        },
        "donor2016": {
            "donors": 0,
            "receipts": 0,
            "amt": 0
        },
        "clinton2016": {
            "donors": 0,
            "receipts": 0,
            "amt": 0
        },
        "sanders2016": {
            "donors": 0,
            "receipts": 0,
            "amt": 0
        },
        "obama2012": {
            "donors": 0,
            "receipts": 0,
            "amt": 0
        },
        "traitor": {
            "donors": 0,
            "receipts": 0,
            "amt": 0
        },
        "elite": {
            "donors": 0,
            "receipts": 0,
            "amt": 0
        },
        "party": {
            "donors": 0,
            "receipts": 0,
            "amt": 0
        },
        "nationalParty": {
            "donors": 0,
            "receipts": 0,
            "amt": 0
        },
        "stateParty": {
            "donors": 0,
            "receipts": 0,
            "amt": 0
        },
        "localParty": {
            "donors": 0,
            "receipts": 0,
            "amt": 0
        },
        "competitorEndorsement": {
            "donors": 0,
            "receipts": 0,
            "amt": 0
        },
        "congressionalEndorsement": {
            "donors": 0,
            "receipts": 0,
            "amt": 0
        },
        "senateEndorsement": {
            "donors": 0,
            "receipts": 0,
            "amt": 0
        },
        "houseEndorsement": {
            "donors": 0,
            "receipts": 0,
            "amt": 0
        }
    },
    "prior": {
        "oneDollar": {
            "donors": 51,
            "receipts": 51,
            "amt": 51
        },
        "oneToTwoHundredDollars": {
            "donors": 987,
            "receipts": 1605,
            "amt": 42946.25
        },
        "twoHundredToOneThousandDollars": {
            "donors": 214,
            "receipts": 674,
            "amt": 86886.3
        },
        "oneThousandToTwentyEightHundredDollars": {
            "donors": 110,
            "receipts": 257,
            "amt": 153068.8
        },
        "twentyEightHundredDollars": {
            "donors": 159,
            "receipts": 255,
            "amt": 510483
        },
        "full2020PrimaryCycle": {
            "donors": 1521,
            "receipts": 2842,
            "amt": 793435.35
        },
        "pre2019": {
            "donors": 27,
            "receipts": 38,
            "amt": 19378
        },
        "q12019": {
            "donors": 112,
            "receipts": 147,
            "amt": 151860
        },
        "q22019": {
            "donors": 1385,
            "receipts": 2211,
            "amt": 522817.55
        },
        "q32019": {
            "donors": 260,
            "receipts": 444,
            "amt": 97879.8
        },
        "q42019": {
            "donors": 1,
            "receipts": 1,
            "amt": 500
        },
        "q12020": {
            "donors": 1,
            "receipts": 1,
            "amt": 1000
        },
        "debate1": {
            "donors": 1335,
            "receipts": 1968,
            "amt": 549681.55
        },
        "debate2": {
            "donors": 346,
            "receipts": 516,
            "amt": 149155
        },
        "debate3": {
            "donors": 192,
            "receipts": 305,
            "amt": 68790.8
        },
        "debate4": {
            "donors": 13,
            "receipts": 13,
            "amt": 4930
        },
        "debate5": {
            "donors": 1,
            "receipts": 1,
            "amt": 500
        },
        "debate6": {
            "donors": 0,
            "receipts": 0,
            "amt": 0
        },
        "debate7": {
            "donors": 0,
            "receipts": 0,
            "amt": 0
        },
        "inState": {
            "donors": 967,
            "receipts": 1868,
            "amt": 385775.25
        },
        "outOfState": {
            "donors": 554,
            "receipts": 974,
            "amt": 407660.1
        },
        "prior": {
            "donors": 1521,
            "receipts": 2842,
            "amt": 793435.35
        },
        "loyal": {
            "donors": 524,
            "receipts": 825,
            "amt": 392570.8
        },
        "donor2016": {
            "donors": 405,
            "receipts": 803,
            "amt": 139931.25
        },
        "clinton2016": {
            "donors": 245,
            "receipts": 476,
            "amt": 106366.8
        },
        "sanders2016": {
            "donors": 204,
            "receipts": 418,
            "amt": 25993.35
        },
        "obama2012": {
            "donors": 102,
            "receipts": 196,
            "amt": 74145.2
        },
        "traitor": {
            "donors": 11,
            "receipts": 30,
            "amt": 2931.4
        },
        "elite": {
            "donors": 1423,
            "receipts": 2726,
            "amt": 768686.55
        },
        "party": {
            "donors": 1200,
            "receipts": 2419,
            "amt": 522938.55
        },
        "nationalParty": {
            "donors": 1160,
            "receipts": 2367,
            "amt": 486742.55
        },
        "stateParty": {
            "donors": 639,
            "receipts": 1433,
            "amt": 280899.7
        },
        "localParty": {
            "donors": 169,
            "receipts": 392,
            "amt": 102175.9
        },
        "competitorEndorsement": {
            "donors": 0,
            "receipts": 0,
            "amt": 0
        },
        "congressionalEndorsement": {
            "donors": 0,
            "receipts": 0,
            "amt": 0
        },
        "senateEndorsement": {
            "donors": 0,
            "receipts": 0,
            "amt": 0
        },
        "houseEndorsement": {
            "donors": 0,
            "receipts": 0,
            "amt": 0
        }
    },
    "priorCampaign": {
        "oneDollar": {
            "donors": 43,
            "receipts": 43,
            "amt": 43
        },
        "oneToTwoHundredDollars": {
            "donors": 903,
            "receipts": 1477,
            "amt": 39414.45
        },
        "twoHundredToOneThousandDollars": {
            "donors": 189,
            "receipts": 616,
            "amt": 77409.5
        },
        "oneThousandToTwentyEightHundredDollars": {
            "donors": 101,
            "receipts": 245,
            "amt": 143018.8
        },
        "twentyEightHundredDollars": {
            "donors": 148,
            "receipts": 241,
            "amt": 473083
        },
        "full2020PrimaryCycle": {
            "donors": 1384,
            "receipts": 2622,
            "amt": 732968.75
        },
        "pre2019": {
            "donors": 27,
            "receipts": 38,
            "amt": 19378
        },
        "q12019": {
            "donors": 112,
            "receipts": 147,
            "amt": 151860
        },
        "q22019": {
            "donors": 1260,
            "receipts": 2033,
            "amt": 472645.55
        },
        "q32019": {
            "donors": 232,
            "receipts": 402,
            "amt": 87585.2
        },
        "q42019": {
            "donors": 1,
            "receipts": 1,
            "amt": 500
        },
        "q12020": {
            "donors": 1,
            "receipts": 1,
            "amt": 1000
        },
        "debate1": {
            "donors": 1220,
            "receipts": 1815,
            "amt": 504026.55
        },
        "debate2": {
            "donors": 317,
            "receipts": 478,
            "amt": 138866.2
        },
        "debate3": {
            "donors": 173,
            "receipts": 277,
            "amt": 65068
        },
        "debate4": {
            "donors": 12,
            "receipts": 12,
            "amt": 4130
        },
        "debate5": {
            "donors": 1,
            "receipts": 1,
            "amt": 500
        },
        "debate6": {
            "donors": 0,
            "receipts": 0,
            "amt": 0
        },
        "debate7": {
            "donors": 0,
            "receipts": 0,
            "amt": 0
        },
        "inState": {
            "donors": 906,
            "receipts": 1779,
            "amt": 355086.75
        },
        "outOfState": {
            "donors": 478,
            "receipts": 843,
            "amt": 377882
        },
        "prior": {
            "donors": 1384,
            "receipts": 2622,
            "amt": 732968.75
        },
        "loyal": {
            "donors": 495,
            "receipts": 784,
            "amt": 369957.6
        },
        "donor2016": {
            "donors": 368,
            "receipts": 738,
            "amt": 137683.85
        },
        "clinton2016": {
            "donors": 225,
            "receipts": 446,
            "amt": 104611.2
        },
        "sanders2016": {
            "donors": 186,
            "receipts": 381,
            "amt": 25486.55
        },
        "obama2012": {
            "donors": 91,
            "receipts": 183,
            "amt": 72315
        },
        "traitor": {
            "donors": 11,
            "receipts": 30,
            "amt": 2931.4
        },
        "elite": {
            "donors": 1286,
            "receipts": 2506,
            "amt": 708219.95
        },
        "party": {
            "donors": 1094,
            "receipts": 2234,
            "amt": 489875.15
        },
        "nationalParty": {
            "donors": 1057,
            "receipts": 2186,
            "amt": 459629.15
        },
        "stateParty": {
            "donors": 569,
            "receipts": 1307,
            "amt": 263844
        },
        "localParty": {
            "donors": 146,
            "receipts": 338,
            "amt": 96342.2
        },
        "competitorEndorsement": {
            "donors": 0,
            "receipts": 0,
            "amt": 0
        },
        "congressionalEndorsement": {
            "donors": 0,
            "receipts": 0,
            "amt": 0
        },
        "senateEndorsement": {
            "donors": 0,
            "receipts": 0,
            "amt": 0
        },
        "houseEndorsement": {
            "donors": 0,
            "receipts": 0,
            "amt": 0
        }
    },
    "priorLeadershipPac": {
        "oneDollar": {
            "donors": 11,
            "receipts": 11,
            "amt": 11
        },
        "oneToTwoHundredDollars": {
            "donors": 177,
            "receipts": 315,
            "amt": 8923.05
        },
        "twoHundredToOneThousandDollars": {
            "donors": 69,
            "receipts": 214,
            "amt": 28154.2
        },
        "oneThousandToTwentyEightHundredDollars": {
            "donors": 48,
            "receipts": 114,
            "amt": 65741.4
        },
        "twentyEightHundredDollars": {
            "donors": 76,
            "receipts": 130,
            "amt": 263273
        },
        "full2020PrimaryCycle": {
            "donors": 381,
            "receipts": 784,
            "amt": 366102.65
        },
        "pre2019": {
            "donors": 10,
            "receipts": 12,
            "amt": 7650
        },
        "q12019": {
            "donors": 49,
            "receipts": 63,
            "amt": 78105
        },
        "q22019": {
            "donors": 327,
            "receipts": 577,
            "amt": 223768.55
        },
        "q32019": {
            "donors": 83,
            "receipts": 132,
            "amt": 56579.1
        },
        "q42019": {
            "donors": 0,
            "receipts": 0,
            "amt": 0
        },
        "q12020": {
            "donors": 0,
            "receipts": 0,
            "amt": 0
        },
        "debate1": {
            "donors": 325,
            "receipts": 533,
            "amt": 250113.75
        },
        "debate2": {
            "donors": 98,
            "receipts": 153,
            "amt": 71763.5
        },
        "debate3": {
            "donors": 53,
            "receipts": 80,
            "amt": 33565.4
        },
        "debate4": {
            "donors": 6,
            "receipts": 6,
            "amt": 3010
        },
        "debate5": {
            "donors": 0,
            "receipts": 0,
            "amt": 0
        },
        "debate6": {
            "donors": 0,
            "receipts": 0,
            "amt": 0
        },
        "debate7": {
            "donors": 0,
            "receipts": 0,
            "amt": 0
        },
        "inState": {
            "donors": 216,
            "receipts": 493,
            "amt": 182639.35
        },
        "outOfState": {
            "donors": 165,
            "receipts": 291,
            "amt": 183463.3
        },
        "prior": {
            "donors": 381,
            "receipts": 784,
            "amt": 366102.65
        },
        "loyal": {
            "donors": 117,
            "receipts": 201,
            "amt": 161487.6
        },
        "donor2016": {
            "donors": 109,
            "receipts": 240,
            "amt": 67629.75
        },
        "clinton2016": {
            "donors": 69,
            "receipts": 133,
            "amt": 44948.6
        },
        "sanders2016": {
            "donors": 43,
            "receipts": 113,
            "amt": 13491.15
        },
        "obama2012": {
            "donors": 40,
            "receipts": 82,
            "amt": 41509.6
        },
        "traitor": {
            "donors": 1,
            "receipts": 1,
            "amt": 1000
        },
        "elite": {
            "donors": 381,
            "receipts": 784,
            "amt": 366102.65
        },
        "party": {
            "donors": 303,
            "receipts": 668,
            "amt": 257058.85
        },
        "nationalParty": {
            "donors": 295,
            "receipts": 658,
            "amt": 250113.65
        },
        "stateParty": {
            "donors": 198,
            "receipts": 459,
            "amt": 150006.8
        },
        "localParty": {
            "donors": 68,
            "receipts": 187,
            "amt": 68244.9
        },
        "competitorEndorsement": {
            "donors": 0,
            "receipts": 0,
            "amt": 0
        },
        "congressionalEndorsement": {
            "donors": 0,
            "receipts": 0,
            "amt": 0
        },
        "senateEndorsement": {
            "donors": 0,
            "receipts": 0,
            "amt": 0
        },
        "houseEndorsement": {
            "donors": 0,
            "receipts": 0,
            "amt": 0
        }
    },
    "endorsement": {
        "oneDollar": {
            "donors": 0,
            "receipts": 0,
            "amt": 0
        },
        "oneToTwoHundredDollars": {
            "donors": 0,
            "receipts": 0,
            "amt": 0
        },
        "twoHundredToOneThousandDollars": {
            "donors": 0,
            "receipts": 0,
            "amt": 0
        },
        "oneThousandToTwentyEightHundredDollars": {
            "donors": 0,
            "receipts": 0,
            "amt": 0
        },
        "twentyEightHundredDollars": {
            "donors": 0,
            "receipts": 0,
            "amt": 0
        },
        "full2020PrimaryCycle": {
            "donors": 0,
            "receipts": 0,
            "amt": 0
        },
        "pre2019": {
            "donors": 0,
            "receipts": 0,
            "amt": 0
        },
        "q12019": {
            "donors": 0,
            "receipts": 0,
            "amt": 0
        },
        "q22019": {
            "donors": 0,
            "receipts": 0,
            "amt": 0
        },
        "q32019": {
            "donors": 0,
            "receipts": 0,
            "amt": 0
        },
        "q42019": {
            "donors": 0,
            "receipts": 0,
            "amt": 0
        },
        "q12020": {
            "donors": 0,
            "receipts": 0,
            "amt": 0
        },
        "debate1": {
            "donors": 0,
            "receipts": 0,
            "amt": 0
        },
        "debate2": {
            "donors": 0,
            "receipts": 0,
            "amt": 0
        },
        "debate3": {
            "donors": 0,
            "receipts": 0,
            "amt": 0
        },
        "debate4": {
            "donors": 0,
            "receipts": 0,
            "amt": 0
        },
        "debate5": {
            "donors": 0,
            "receipts": 0,
            "amt": 0
        },
        "debate6": {
            "donors": 0,
            "receipts": 0,
            "amt": 0
        },
        "debate7": {
            "donors": 0,
            "receipts": 0,
            "amt": 0
        },
        "inState": {
            "donors": 0,
            "receipts": 0,
            "amt": 0
        },
        "outOfState": {
            "donors": 0,
            "receipts": 0,
            "amt": 0
        },
        "prior": {
            "donors": 0,
            "receipts": 0,
            "amt": 0
        },
        "loyal": {
            "donors": 0,
            "receipts": 0,
            "amt": 0
        },
        "donor2016": {
            "donors": 0,
            "receipts": 0,
            "amt": 0
        },
        "clinton2016": {
            "donors": 0,
            "receipts": 0,
            "amt": 0
        },
        "sanders2016": {
            "donors": 0,
            "receipts": 0,
            "amt": 0
        },
        "obama2012": {
            "donors": 0,
            "receipts": 0,
            "amt": 0
        },
        "traitor": {
            "donors": 0,
            "receipts": 0,
            "amt": 0
        },
        "elite": {
            "donors": 0,
            "receipts": 0,
            "amt": 0
        },
        "party": {
            "donors": 0,
            "receipts": 0,
            "amt": 0
        },
        "nationalParty": {
            "donors": 0,
            "receipts": 0,
            "amt": 0
        },
        "stateParty": {
            "donors": 0,
            "receipts": 0,
            "amt": 0
        },
        "localParty": {
            "donors": 0,
            "receipts": 0,
            "amt": 0
        },
        "competitorEndorsement": {
            "donors": 0,
            "receipts": 0,
            "amt": 0
        },
        "congressionalEndorsement": {
            "donors": 0,
            "receipts": 0,
            "amt": 0
        },
        "senateEndorsement": {
            "donors": 0,
            "receipts": 0,
            "amt": 0
        },
        "houseEndorsement": {
            "donors": 0,
            "receipts": 0,
            "amt": 0
        }
    },
    "endorsementPre": {
        "oneDollar": {
            "donors": 0,
            "receipts": 0,
            "amt": 0
        },
        "oneToTwoHundredDollars": {
            "donors": 0,
            "receipts": 0,
            "amt": 0
        },
        "twoHundredToOneThousandDollars": {
            "donors": 0,
            "receipts": 0,
            "amt": 0
        },
        "oneThousandToTwentyEightHundredDollars": {
            "donors": 0,
            "receipts": 0,
            "amt": 0
        },
        "twentyEightHundredDollars": {
            "donors": 0,
            "receipts": 0,
            "amt": 0
        },
        "full2020PrimaryCycle": {
            "donors": 0,
            "receipts": 0,
            "amt": 0
        },
        "pre2019": {
            "donors": 0,
            "receipts": 0,
            "amt": 0
        },
        "q12019": {
            "donors": 0,
            "receipts": 0,
            "amt": 0
        },
        "q22019": {
            "donors": 0,
            "receipts": 0,
            "amt": 0
        },
        "q32019": {
            "donors": 0,
            "receipts": 0,
            "amt": 0
        },
        "q42019": {
            "donors": 0,
            "receipts": 0,
            "amt": 0
        },
        "q12020": {
            "donors": 0,
            "receipts": 0,
            "amt": 0
        },
        "debate1": {
            "donors": 0,
            "receipts": 0,
            "amt": 0
        },
        "debate2": {
            "donors": 0,
            "receipts": 0,
            "amt": 0
        },
        "debate3": {
            "donors": 0,
            "receipts": 0,
            "amt": 0
        },
        "debate4": {
            "donors": 0,
            "receipts": 0,
            "amt": 0
        },
        "debate5": {
            "donors": 0,
            "receipts": 0,
            "amt": 0
        },
        "debate6": {
            "donors": 0,
            "receipts": 0,
            "amt": 0
        },
        "debate7": {
            "donors": 0,
            "receipts": 0,
            "amt": 0
        },
        "inState": {
            "donors": 0,
            "receipts": 0,
            "amt": 0
        },
        "outOfState": {
            "donors": 0,
            "receipts": 0,
            "amt": 0
        },
        "prior": {
            "donors": 0,
            "receipts": 0,
            "amt": 0
        },
        "loyal": {
            "donors": 0,
            "receipts": 0,
            "amt": 0
        },
        "donor2016": {
            "donors": 0,
            "receipts": 0,
            "amt": 0
        },
        "clinton2016": {
            "donors": 0,
            "receipts": 0,
            "amt": 0
        },
        "sanders2016": {
            "donors": 0,
            "receipts": 0,
            "amt": 0
        },
        "obama2012": {
            "donors": 0,
            "receipts": 0,
            "amt": 0
        },
        "traitor": {
            "donors": 0,
            "receipts": 0,
            "amt": 0
        },
        "elite": {
            "donors": 0,
            "receipts": 0,
            "amt": 0
        },
        "party": {
            "donors": 0,
            "receipts": 0,
            "amt": 0
        },
        "nationalParty": {
            "donors": 0,
            "receipts": 0,
            "amt": 0
        },
        "stateParty": {
            "donors": 0,
            "receipts": 0,
            "amt": 0
        },
        "localParty": {
            "donors": 0,
            "receipts": 0,
            "amt": 0
        },
        "competitorEndorsement": {
            "donors": 0,
            "receipts": 0,
            "amt": 0
        },
        "congressionalEndorsement": {
            "donors": 0,
            "receipts": 0,
            "amt": 0
        },
        "senateEndorsement": {
            "donors": 0,
            "receipts": 0,
            "amt": 0
        },
        "houseEndorsement": {
            "donors": 0,
            "receipts": 0,
            "amt": 0
        }
    },
    "endorsementPost": {
        "oneDollar": {
            "donors": 0,
            "receipts": 0,
            "amt": 0
        },
        "oneToTwoHundredDollars": {
            "donors": 0,
            "receipts": 0,
            "amt": 0
        },
        "twoHundredToOneThousandDollars": {
            "donors": 0,
            "receipts": 0,
            "amt": 0
        },
        "oneThousandToTwentyEightHundredDollars": {
            "donors": 0,
            "receipts": 0,
            "amt": 0
        },
        "twentyEightHundredDollars": {
            "donors": 0,
            "receipts": 0,
            "amt": 0
        },
        "full2020PrimaryCycle": {
            "donors": 0,
            "receipts": 0,
            "amt": 0
        },
        "pre2019": {
            "donors": 0,
            "receipts": 0,
            "amt": 0
        },
        "q12019": {
            "donors": 0,
            "receipts": 0,
            "amt": 0
        },
        "q22019": {
            "donors": 0,
            "receipts": 0,
            "amt": 0
        },
        "q32019": {
            "donors": 0,
            "receipts": 0,
            "amt": 0
        },
        "q42019": {
            "donors": 0,
            "receipts": 0,
            "amt": 0
        },
        "q12020": {
            "donors": 0,
            "receipts": 0,
            "amt": 0
        },
        "debate1": {
            "donors": 0,
            "receipts": 0,
            "amt": 0
        },
        "debate2": {
            "donors": 0,
            "receipts": 0,
            "amt": 0
        },
        "debate3": {
            "donors": 0,
            "receipts": 0,
            "amt": 0
        },
        "debate4": {
            "donors": 0,
            "receipts": 0,
            "amt": 0
        },
        "debate5": {
            "donors": 0,
            "receipts": 0,
            "amt": 0
        },
        "debate6": {
            "donors": 0,
            "receipts": 0,
            "amt": 0
        },
        "debate7": {
            "donors": 0,
            "receipts": 0,
            "amt": 0
        },
        "inState": {
            "donors": 0,
            "receipts": 0,
            "amt": 0
        },
        "outOfState": {
            "donors": 0,
            "receipts": 0,
            "amt": 0
        },
        "prior": {
            "donors": 0,
            "receipts": 0,
            "amt": 0
        },
        "loyal": {
            "donors": 0,
            "receipts": 0,
            "amt": 0
        },
        "donor2016": {
            "donors": 0,
            "receipts": 0,
            "amt": 0
        },
        "clinton2016": {
            "donors": 0,
            "receipts": 0,
            "amt": 0
        },
        "sanders2016": {
            "donors": 0,
            "receipts": 0,
            "amt": 0
        },
        "obama2012": {
            "donors": 0,
            "receipts": 0,
            "amt": 0
        },
        "traitor": {
            "donors": 0,
            "receipts": 0,
            "amt": 0
        },
        "elite": {
            "donors": 0,
            "receipts": 0,
            "amt": 0
        },
        "party": {
            "donors": 0,
            "receipts": 0,
            "amt": 0
        },
        "nationalParty": {
            "donors": 0,
            "receipts": 0,
            "amt": 0
        },
        "stateParty": {
            "donors": 0,
            "receipts": 0,
            "amt": 0
        },
        "localParty": {
            "donors": 0,
            "receipts": 0,
            "amt": 0
        },
        "competitorEndorsement": {
            "donors": 0,
            "receipts": 0,
            "amt": 0
        },
        "congressionalEndorsement": {
            "donors": 0,
            "receipts": 0,
            "amt": 0
        },
        "senateEndorsement": {
            "donors": 0,
            "receipts": 0,
            "amt": 0
        },
        "houseEndorsement": {
            "donors": 0,
            "receipts": 0,
            "amt": 0
        }
    },
    "congressionalEndorsement": {
        "oneDollar": {
            "donors": 0,
            "receipts": 0,
            "amt": 0
        },
        "oneToTwoHundredDollars": {
            "donors": 0,
            "receipts": 0,
            "amt": 0
        },
        "twoHundredToOneThousandDollars": {
            "donors": 0,
            "receipts": 0,
            "amt": 0
        },
        "oneThousandToTwentyEightHundredDollars": {
            "donors": 0,
            "receipts": 0,
            "amt": 0
        },
        "twentyEightHundredDollars": {
            "donors": 0,
            "receipts": 0,
            "amt": 0
        },
        "full2020PrimaryCycle": {
            "donors": 0,
            "receipts": 0,
            "amt": 0
        },
        "pre2019": {
            "donors": 0,
            "receipts": 0,
            "amt": 0
        },
        "q12019": {
            "donors": 0,
            "receipts": 0,
            "amt": 0
        },
        "q22019": {
            "donors": 0,
            "receipts": 0,
            "amt": 0
        },
        "q32019": {
            "donors": 0,
            "receipts": 0,
            "amt": 0
        },
        "q42019": {
            "donors": 0,
            "receipts": 0,
            "amt": 0
        },
        "q12020": {
            "donors": 0,
            "receipts": 0,
            "amt": 0
        },
        "debate1": {
            "donors": 0,
            "receipts": 0,
            "amt": 0
        },
        "debate2": {
            "donors": 0,
            "receipts": 0,
            "amt": 0
        },
        "debate3": {
            "donors": 0,
            "receipts": 0,
            "amt": 0
        },
        "debate4": {
            "donors": 0,
            "receipts": 0,
            "amt": 0
        },
        "debate5": {
            "donors": 0,
            "receipts": 0,
            "amt": 0
        },
        "debate6": {
            "donors": 0,
            "receipts": 0,
            "amt": 0
        },
        "debate7": {
            "donors": 0,
            "receipts": 0,
            "amt": 0
        },
        "inState": {
            "donors": 0,
            "receipts": 0,
            "amt": 0
        },
        "outOfState": {
            "donors": 0,
            "receipts": 0,
            "amt": 0
        },
        "prior": {
            "donors": 0,
            "receipts": 0,
            "amt": 0
        },
        "loyal": {
            "donors": 0,
            "receipts": 0,
            "amt": 0
        },
        "donor2016": {
            "donors": 0,
            "receipts": 0,
            "amt": 0
        },
        "clinton2016": {
            "donors": 0,
            "receipts": 0,
            "amt": 0
        },
        "sanders2016": {
            "donors": 0,
            "receipts": 0,
            "amt": 0
        },
        "obama2012": {
            "donors": 0,
            "receipts": 0,
            "amt": 0
        },
        "traitor": {
            "donors": 0,
            "receipts": 0,
            "amt": 0
        },
        "elite": {
            "donors": 0,
            "receipts": 0,
            "amt": 0
        },
        "party": {
            "donors": 0,
            "receipts": 0,
            "amt": 0
        },
        "nationalParty": {
            "donors": 0,
            "receipts": 0,
            "amt": 0
        },
        "stateParty": {
            "donors": 0,
            "receipts": 0,
            "amt": 0
        },
        "localParty": {
            "donors": 0,
            "receipts": 0,
            "amt": 0
        },
        "competitorEndorsement": {
            "donors": 0,
            "receipts": 0,
            "amt": 0
        },
        "congressionalEndorsement": {
            "donors": 0,
            "receipts": 0,
            "amt": 0
        },
        "senateEndorsement": {
            "donors": 0,
            "receipts": 0,
            "amt": 0
        },
        "houseEndorsement": {
            "donors": 0,
            "receipts": 0,
            "amt": 0
        }
    },
    "competitorEndorsement": {
        "oneDollar": {
            "donors": 0,
            "receipts": 0,
            "amt": 0
        },
        "oneToTwoHundredDollars": {
            "donors": 0,
            "receipts": 0,
            "amt": 0
        },
        "twoHundredToOneThousandDollars": {
            "donors": 0,
            "receipts": 0,
            "amt": 0
        },
        "oneThousandToTwentyEightHundredDollars": {
            "donors": 0,
            "receipts": 0,
            "amt": 0
        },
        "twentyEightHundredDollars": {
            "donors": 0,
            "receipts": 0,
            "amt": 0
        },
        "full2020PrimaryCycle": {
            "donors": 0,
            "receipts": 0,
            "amt": 0
        },
        "pre2019": {
            "donors": 0,
            "receipts": 0,
            "amt": 0
        },
        "q12019": {
            "donors": 0,
            "receipts": 0,
            "amt": 0
        },
        "q22019": {
            "donors": 0,
            "receipts": 0,
            "amt": 0
        },
        "q32019": {
            "donors": 0,
            "receipts": 0,
            "amt": 0
        },
        "q42019": {
            "donors": 0,
            "receipts": 0,
            "amt": 0
        },
        "q12020": {
            "donors": 0,
            "receipts": 0,
            "amt": 0
        },
        "debate1": {
            "donors": 0,
            "receipts": 0,
            "amt": 0
        },
        "debate2": {
            "donors": 0,
            "receipts": 0,
            "amt": 0
        },
        "debate3": {
            "donors": 0,
            "receipts": 0,
            "amt": 0
        },
        "debate4": {
            "donors": 0,
            "receipts": 0,
            "amt": 0
        },
        "debate5": {
            "donors": 0,
            "receipts": 0,
            "amt": 0
        },
        "debate6": {
            "donors": 0,
            "receipts": 0,
            "amt": 0
        },
        "debate7": {
            "donors": 0,
            "receipts": 0,
            "amt": 0
        },
        "inState": {
            "donors": 0,
            "receipts": 0,
            "amt": 0
        },
        "outOfState": {
            "donors": 0,
            "receipts": 0,
            "amt": 0
        },
        "prior": {
            "donors": 0,
            "receipts": 0,
            "amt": 0
        },
        "loyal": {
            "donors": 0,
            "receipts": 0,
            "amt": 0
        },
        "donor2016": {
            "donors": 0,
            "receipts": 0,
            "amt": 0
        },
        "clinton2016": {
            "donors": 0,
            "receipts": 0,
            "amt": 0
        },
        "sanders2016": {
            "donors": 0,
            "receipts": 0,
            "amt": 0
        },
        "obama2012": {
            "donors": 0,
            "receipts": 0,
            "amt": 0
        },
        "traitor": {
            "donors": 0,
            "receipts": 0,
            "amt": 0
        },
        "elite": {
            "donors": 0,
            "receipts": 0,
            "amt": 0
        },
        "party": {
            "donors": 0,
            "receipts": 0,
            "amt": 0
        },
        "nationalParty": {
            "donors": 0,
            "receipts": 0,
            "amt": 0
        },
        "stateParty": {
            "donors": 0,
            "receipts": 0,
            "amt": 0
        },
        "localParty": {
            "donors": 0,
            "receipts": 0,
            "amt": 0
        },
        "competitorEndorsement": {
            "donors": 0,
            "receipts": 0,
            "amt": 0
        },
        "congressionalEndorsement": {
            "donors": 0,
            "receipts": 0,
            "amt": 0
        },
        "senateEndorsement": {
            "donors": 0,
            "receipts": 0,
            "amt": 0
        },
        "houseEndorsement": {
            "donors": 0,
            "receipts": 0,
            "amt": 0
        }
    },
    "nonEndorsement": {
        "oneDollar": {
            "donors": 2652,
            "receipts": 2652,
            "amt": 2652
        },
        "oneToTwoHundredDollars": {
            "donors": 11428,
            "receipts": 15576,
            "amt": 292597.31
        },
        "twoHundredToOneThousandDollars": {
            "donors": 556,
            "receipts": 1637,
            "amt": 208484.8
        },
        "oneThousandToTwentyEightHundredDollars": {
            "donors": 211,
            "receipts": 457,
            "amt": 279259
        },
        "twentyEightHundredDollars": {
            "donors": 227,
            "receipts": 343,
            "amt": 716115.4
        },
        "full2020PrimaryCycle": {
            "donors": 15074,
            "receipts": 20665,
            "amt": 1499108.51
        },
        "pre2019": {
            "donors": 27,
            "receipts": 38,
            "amt": 19378
        },
        "q12019": {
            "donors": 122,
            "receipts": 157,
            "amt": 163385
        },
        "q22019": {
            "donors": 13822,
            "receipts": 17369,
            "amt": 1092642.05
        },
        "q32019": {
            "donors": 2167,
            "receipts": 3096,
            "amt": 221678.26
        },
        "q42019": {
            "donors": 2,
            "receipts": 2,
            "amt": 1000
        },
        "q12020": {
            "donors": 2,
            "receipts": 2,
            "amt": 1005
        },
        "debate1": {
            "donors": 12797,
            "receipts": 15033,
            "amt": 1005100.26
        },
        "debate2": {
            "donors": 2724,
            "receipts": 3546,
            "amt": 310349.37
        },
        "debate3": {
            "donors": 1520,
            "receipts": 2023,
            "amt": 153375.68
        },
        "debate4": {
            "donors": 20,
            "receipts": 20,
            "amt": 8880
        },
        "debate5": {
            "donors": 2,
            "receipts": 2,
            "amt": 1000
        },
        "debate6": {
            "donors": 0,
            "receipts": 0,
            "amt": 0
        },
        "debate7": {
            "donors": 0,
            "receipts": 0,
            "amt": 0
        },
        "inState": {
            "donors": 4403,
            "receipts": 6241,
            "amt": 611473.98
        },
        "outOfState": {
            "donors": 10671,
            "receipts": 14424,
            "amt": 887634.53
        },
        "prior": {
            "donors": 1521,
            "receipts": 2842,
            "amt": 793435.35
        },
        "loyal": {
            "donors": 4542,
            "receipts": 5538,
            "amt": 678628.55
        },
        "donor2016": {
            "donors": 3448,
            "receipts": 5203,
            "amt": 270842.12
        },
        "clinton2016": {
            "donors": 1456,
            "receipts": 2288,
            "amt": 194444.2
        },
        "sanders2016": {
            "donors": 2353,
            "receipts": 3458,
            "amt": 76317.57
        },
        "obama2012": {
            "donors": 477,
            "receipts": 708,
            "amt": 116630.98
        },
        "traitor": {
            "donors": 111,
            "receipts": 146,
            "amt": 10537
        },
        "elite": {
            "donors": 11557,
            "receipts": 16772,
            "amt": 1390179.88
        },
        "party": {
            "donors": 10317,
            "receipts": 15249,
            "amt": 958218.74
        },
        "nationalParty": {
            "donors": 10013,
            "receipts": 14900,
            "amt": 893242.71
        },
        "stateParty": {
            "donors": 5292,
            "receipts": 8419,
            "amt": 474014.04
        },
        "localParty": {
            "donors": 847,
            "receipts": 1567,
            "amt": 138034.44
        },
        "competitorEndorsement": {
            "donors": 0,
            "receipts": 0,
            "amt": 0
        },
        "congressionalEndorsement": {
            "donors": 0,
            "receipts": 0,
            "amt": 0
        },
        "senateEndorsement": {
            "donors": 0,
            "receipts": 0,
            "amt": 0
        },
        "houseEndorsement": {
            "donors": 0,
            "receipts": 0,
            "amt": 0
        }
    },
    "unfaithful": {
        "oneDollar": {
            "donors": 1733,
            "receipts": 1733,
            "amt": 1733
        },
        "oneToTwoHundredDollars": {
            "donors": 8273,
            "receipts": 11828,
            "amt": 197075.76
        },
        "twoHundredToOneThousandDollars": {
            "donors": 309,
            "receipts": 1116,
            "amt": 115202.6
        },
        "oneThousandToTwentyEightHundredDollars": {
            "donors": 103,
            "receipts": 289,
            "amt": 141087.6
        },
        "twentyEightHundredDollars": {
            "donors": 114,
            "receipts": 161,
            "amt": 365381
        },
        "full2020PrimaryCycle": {
            "donors": 10532,
            "receipts": 15127,
            "amt": 820479.96
        },
        "pre2019": {
            "donors": 12,
            "receipts": 17,
            "amt": 7380
        },
        "q12019": {
            "donors": 61,
            "receipts": 85,
            "amt": 75930
        },
        "q22019": {
            "donors": 9566,
            "receipts": 12486,
            "amt": 597397.37
        },
        "q32019": {
            "donors": 1723,
            "receipts": 2536,
            "amt": 138252.39
        },
        "q42019": {
            "donors": 1,
            "receipts": 1,
            "amt": 500
        },
        "q12020": {
            "donors": 1,
            "receipts": 1,
            "amt": 1000
        },
        "debate1": {
            "donors": 8767,
            "receipts": 10616,
            "amt": 557261.16
        },
        "debate2": {
            "donors": 2160,
            "receipts": 2832,
            "amt": 154091.83
        },
        "debate3": {
            "donors": 1197,
            "receipts": 1642,
            "amt": 93196.77
        },
        "debate4": {
            "donors": 17,
            "receipts": 17,
            "amt": 7030
        },
        "debate5": {
            "donors": 1,
            "receipts": 1,
            "amt": 500
        },
        "debate6": {
            "donors": 0,
            "receipts": 0,
            "amt": 0
        },
        "debate7": {
            "donors": 0,
            "receipts": 0,
            "amt": 0
        },
        "inState": {
            "donors": 2720,
            "receipts": 4164,
            "amt": 320290.08
        },
        "outOfState": {
            "donors": 7812,
            "receipts": 10963,
            "amt": 500189.88
        },
        "prior": {
            "donors": 997,
            "receipts": 2017,
            "amt": 400864.55
        },
        "loyal": {
            "donors": 0,
            "receipts": 0,
            "amt": 0
        },
        "donor2016": {
            "donors": 3210,
            "receipts": 4899,
            "amt": 230283.92
        },
        "clinton2016": {
            "donors": 1372,
            "receipts": 2189,
            "amt": 167726.2
        },
        "sanders2016": {
            "donors": 2195,
            "receipts": 3249,
            "amt": 62975.97
        },
        "obama2012": {
            "donors": 447,
            "receipts": 668,
            "amt": 109256.18
        },
        "traitor": {
            "donors": 70,
            "receipts": 93,
            "amt": 7990.2
        },
        "elite": {
            "donors": 9609,
            "receipts": 14093,
            "amt": 806035.2
        },
        "party": {
            "donors": 8988,
            "receipts": 13382,
            "amt": 664263.94
        },
        "nationalParty": {
            "donors": 8800,
            "receipts": 13161,
            "amt": 636696.71
        },
        "stateParty": {
            "donors": 4997,
            "receipts": 8013,
            "amt": 373887.94
        },
        "localParty": {
            "donors": 797,
            "receipts": 1498,
            "amt": 108790.64
        },
        "competitorEndorsement": {
            "donors": 0,
            "receipts": 0,
            "amt": 0
        },
        "congressionalEndorsement": {
            "donors": 0,
            "receipts": 0,
            "amt": 0
        },
        "senateEndorsement": {
            "donors": 0,
            "receipts": 0,
            "amt": 0
        },
        "houseEndorsement": {
            "donors": 0,
            "receipts": 0,
            "amt": 0
        }
    },
    "loyal": {
        "oneDollar": {
            "donors": 919,
            "receipts": 919,
            "amt": 919
        },
        "oneToTwoHundredDollars": {
            "donors": 3155,
            "receipts": 3748,
            "amt": 95521.55
        },
        "twoHundredToOneThousandDollars": {
            "donors": 247,
            "receipts": 521,
            "amt": 93282.2
        },
        "oneThousandToTwentyEightHundredDollars": {
            "donors": 108,
            "receipts": 168,
            "amt": 138171.4
        },
        "twentyEightHundredDollars": {
            "donors": 113,
            "receipts": 182,
            "amt": 350734.4
        },
        "full2020PrimaryCycle": {
            "donors": 4542,
            "receipts": 5538,
            "amt": 678628.55
        },
        "pre2019": {
            "donors": 15,
            "receipts": 21,
            "amt": 11998
        },
        "q12019": {
            "donors": 61,
            "receipts": 72,
            "amt": 87455
        },
        "q22019": {
            "donors": 4256,
            "receipts": 4883,
            "amt": 495244.68
        },
        "q32019": {
            "donors": 444,
            "receipts": 560,
            "amt": 83425.87
        },
        "q42019": {
            "donors": 1,
            "receipts": 1,
            "amt": 500
        },
        "q12020": {
            "donors": 1,
            "receipts": 1,
            "amt": 5
        },
        "debate1": {
            "donors": 4030,
            "receipts": 4417,
            "amt": 447839.1
        },
        "debate2": {
            "donors": 564,
            "receipts": 714,
            "amt": 156257.54
        },
        "debate3": {
            "donors": 323,
            "receipts": 381,
            "amt": 60178.91
        },
        "debate4": {
            "donors": 3,
            "receipts": 3,
            "amt": 1850
        },
        "debate5": {
            "donors": 1,
            "receipts": 1,
            "amt": 500
        },
        "debate6": {
            "donors": 0,
            "receipts": 0,
            "amt": 0
        },
        "debate7": {
            "donors": 0,
            "receipts": 0,
            "amt": 0
        },
        "inState": {
            "donors": 1683,
            "receipts": 2077,
            "amt": 291183.9
        },
        "outOfState": {
            "donors": 2859,
            "receipts": 3461,
            "amt": 387444.65
        },
        "prior": {
            "donors": 524,
            "receipts": 825,
            "amt": 392570.8
        },
        "loyal": {
            "donors": 4542,
            "receipts": 5538,
            "amt": 678628.55
        },
        "donor2016": {
            "donors": 238,
            "receipts": 304,
            "amt": 40558.2
        },
        "clinton2016": {
            "donors": 84,
            "receipts": 99,
            "amt": 26718
        },
        "sanders2016": {
            "donors": 158,
            "receipts": 209,
            "amt": 13341.6
        },
        "obama2012": {
            "donors": 30,
            "receipts": 40,
            "amt": 7374.8
        },
        "traitor": {
            "donors": 41,
            "receipts": 53,
            "amt": 2546.8
        },
        "elite": {
            "donors": 1948,
            "receipts": 2679,
            "amt": 584144.68
        },
        "party": {
            "donors": 1329,
            "receipts": 1867,
            "amt": 293954.8
        },
        "nationalParty": {
            "donors": 1213,
            "receipts": 1739,
            "amt": 256546
        },
        "stateParty": {
            "donors": 295,
            "receipts": 406,
            "amt": 100126.1
        },
        "localParty": {
            "donors": 50,
            "receipts": 69,
            "amt": 29243.8
        },
        "competitorEndorsement": {
            "donors": 0,
            "receipts": 0,
            "amt": 0
        },
        "congressionalEndorsement": {
            "donors": 0,
            "receipts": 0,
            "amt": 0
        },
        "senateEndorsement": {
            "donors": 0,
            "receipts": 0,
            "amt": 0
        },
        "houseEndorsement": {
            "donors": 0,
            "receipts": 0,
            "amt": 0
        }
    },
    "donor2016": {
        "oneDollar": {
            "donors": 509,
            "receipts": 509,
            "amt": 509
        },
        "oneToTwoHundredDollars": {
            "donors": 2756,
            "receipts": 4132,
            "amt": 68060.12
        },
        "twoHundredToOneThousandDollars": {
            "donors": 112,
            "receipts": 437,
            "amt": 39327.8
        },
        "oneThousandToTwentyEightHundredDollars": {
            "donors": 31,
            "receipts": 66,
            "amt": 40770.2
        },
        "twentyEightHundredDollars": {
            "donors": 40,
            "receipts": 59,
            "amt": 122175
        },
        "full2020PrimaryCycle": {
            "donors": 3448,
            "receipts": 5203,
            "amt": 270842.12
        },
        "pre2019": {
            "donors": 3,
            "receipts": 5,
            "amt": 700
        },
        "q12019": {
            "donors": 21,
            "receipts": 26,
            "amt": 27800
        },
        "q22019": {
            "donors": 3154,
            "receipts": 4280,
            "amt": 204131.49
        },
        "q32019": {
            "donors": 579,
            "receipts": 891,
            "amt": 37210.63
        },
        "q42019": {
            "donors": 0,
            "receipts": 0,
            "amt": 0
        },
        "q12020": {
            "donors": 1,
            "receipts": 1,
            "amt": 1000
        },
        "debate1": {
            "donors": 2847,
            "receipts": 3563,
            "amt": 192734.77
        },
        "debate2": {
            "donors": 793,
            "receipts": 1073,
            "amt": 49565.59
        },
        "debate3": {
            "donors": 392,
            "receipts": 559,
            "amt": 26491.76
        },
        "debate4": {
            "donors": 2,
            "receipts": 2,
            "amt": 350
        },
        "debate5": {
            "donors": 0,
            "receipts": 0,
            "amt": 0
        },
        "debate6": {
            "donors": 0,
            "receipts": 0,
            "amt": 0
        },
        "debate7": {
            "donors": 0,
            "receipts": 0,
            "amt": 0
        },
        "inState": {
            "donors": 880,
            "receipts": 1408,
            "amt": 111656.28
        },
        "outOfState": {
            "donors": 2568,
            "receipts": 3795,
            "amt": 159185.84
        },
        "prior": {
            "donors": 405,
            "receipts": 803,
            "amt": 139931.25
        },
        "loyal": {
            "donors": 238,
            "receipts": 304,
            "amt": 40558.2
        },
        "donor2016": {
            "donors": 3448,
            "receipts": 5203,
            "amt": 270842.12
        },
        "clinton2016": {
            "donors": 1456,
            "receipts": 2288,
            "amt": 194444.2
        },
        "sanders2016": {
            "donors": 2353,
            "receipts": 3458,
            "amt": 76317.57
        },
        "obama2012": {
            "donors": 301,
            "receipts": 443,
            "amt": 59526.98
        },
        "traitor": {
            "donors": 31,
            "receipts": 42,
            "amt": 1256.8
        },
        "elite": {
            "donors": 3376,
            "receipts": 5117,
            "amt": 269226.12
        },
        "party": {
            "donors": 3310,
            "receipts": 5045,
            "amt": 251398.79
        },
        "nationalParty": {
            "donors": 3282,
            "receipts": 5016,
            "amt": 250106.39
        },
        "stateParty": {
            "donors": 2301,
            "receipts": 3667,
            "amt": 162177.37
        },
        "localParty": {
            "donors": 497,
            "receipts": 870,
            "amt": 53973.02
        },
        "competitorEndorsement": {
            "donors": 0,
            "receipts": 0,
            "amt": 0
        },
        "congressionalEndorsement": {
            "donors": 0,
            "receipts": 0,
            "amt": 0
        },
        "senateEndorsement": {
            "donors": 0,
            "receipts": 0,
            "amt": 0
        },
        "houseEndorsement": {
            "donors": 0,
            "receipts": 0,
            "amt": 0
        }
    },
    "clinton2016": {
        "oneDollar": {
            "donors": 154,
            "receipts": 154,
            "amt": 154
        },
        "oneToTwoHundredDollars": {
            "donors": 1164,
            "receipts": 1741,
            "amt": 34049.9
        },
        "twoHundredToOneThousandDollars": {
            "donors": 78,
            "receipts": 301,
            "amt": 28065.1
        },
        "oneThousandToTwentyEightHundredDollars": {
            "donors": 27,
            "receipts": 50,
            "amt": 36220.2
        },
        "twentyEightHundredDollars": {
            "donors": 33,
            "receipts": 42,
            "amt": 95955
        },
        "full2020PrimaryCycle": {
            "donors": 1456,
            "receipts": 2288,
            "amt": 194444.2
        },
        "pre2019": {
            "donors": 1,
            "receipts": 2,
            "amt": 100
        },
        "q12019": {
            "donors": 17,
            "receipts": 17,
            "amt": 24000
        },
        "q22019": {
            "donors": 1331,
            "receipts": 1840,
            "amt": 144218.67
        },
        "q32019": {
            "donors": 257,
            "receipts": 428,
            "amt": 25125.53
        },
        "q42019": {
            "donors": 0,
            "receipts": 0,
            "amt": 0
        },
        "q12020": {
            "donors": 1,
            "receipts": 1,
            "amt": 1000
        },
        "debate1": {
            "donors": 1190,
            "receipts": 1515,
            "amt": 139844.15
        },
        "debate2": {
            "donors": 351,
            "receipts": 491,
            "amt": 35534.49
        },
        "debate3": {
            "donors": 176,
            "receipts": 277,
            "amt": 17615.56
        },
        "debate4": {
            "donors": 2,
            "receipts": 2,
            "amt": 350
        },
        "debate5": {
            "donors": 0,
            "receipts": 0,
            "amt": 0
        },
        "debate6": {
            "donors": 0,
            "receipts": 0,
            "amt": 0
        },
        "debate7": {
            "donors": 0,
            "receipts": 0,
            "amt": 0
        },
        "inState": {
            "donors": 387,
            "receipts": 647,
            "amt": 74756.63
        },
        "outOfState": {
            "donors": 1069,
            "receipts": 1641,
            "amt": 119687.57
        },
        "prior": {
            "donors": 245,
            "receipts": 476,
            "amt": 106366.8
        },
        "loyal": {
            "donors": 84,
            "receipts": 99,
            "amt": 26718
        },
        "donor2016": {
            "donors": 1456,
            "receipts": 2288,
            "amt": 194444.2
        },
        "clinton2016": {
            "donors": 1456,
            "receipts": 2288,
            "amt": 194444.2
        },
        "sanders2016": {
            "donors": 387,
            "receipts": 589,
            "amt": 13339.05
        },
        "obama2012": {
            "donors": 230,
            "receipts": 341,
            "amt": 50567.93
        },
        "traitor": {
            "donors": 7,
            "receipts": 9,
            "amt": 108.2
        },
        "elite": {
            "donors": 1443,
            "receipts": 2271,
            "amt": 193803.8
        },
        "party": {
            "donors": 1410,
            "receipts": 2236,
            "amt": 178832.87
        },
        "nationalParty": {
            "donors": 1398,
            "receipts": 2224,
            "amt": 177845.67
        },
        "stateParty": {
            "donors": 1088,
            "receipts": 1792,
            "amt": 114219.37
        },
        "localParty": {
            "donors": 310,
            "receipts": 536,
            "amt": 31796.62
        },
        "competitorEndorsement": {
            "donors": 0,
            "receipts": 0,
            "amt": 0
        },
        "congressionalEndorsement": {
            "donors": 0,
            "receipts": 0,
            "amt": 0
        },
        "senateEndorsement": {
            "donors": 0,
            "receipts": 0,
            "amt": 0
        },
        "houseEndorsement": {
            "donors": 0,
            "receipts": 0,
            "amt": 0
        }
    },
    "sanders2016": {
        "oneDollar": {
            "donors": 418,
            "receipts": 418,
            "amt": 418
        },
        "oneToTwoHundredDollars": {
            "donors": 1886,
            "receipts": 2854,
            "amt": 39687.97
        },
        "twoHundredToOneThousandDollars": {
            "donors": 37,
            "receipts": 151,
            "amt": 12391.6
        },
        "oneThousandToTwentyEightHundredDollars": {
            "donors": 7,
            "receipts": 22,
            "amt": 8800
        },
        "twentyEightHundredDollars": {
            "donors": 5,
            "receipts": 13,
            "amt": 15020
        },
        "full2020PrimaryCycle": {
            "donors": 2353,
            "receipts": 3458,
            "amt": 76317.57
        },
        "pre2019": {
            "donors": 2,
            "receipts": 3,
            "amt": 600
        },
        "q12019": {
            "donors": 6,
            "receipts": 11,
            "amt": 5050
        },
        "q22019": {
            "donors": 2151,
            "receipts": 2877,
            "amt": 55610.37
        },
        "q32019": {
            "donors": 387,
            "receipts": 567,
            "amt": 15057.2
        },
        "q42019": {
            "donors": 0,
            "receipts": 0,
            "amt": 0
        },
        "q12020": {
            "donors": 0,
            "receipts": 0,
            "amt": 0
        },
        "debate1": {
            "donors": 1937,
            "receipts": 2396,
            "amt": 50543.65
        },
        "debate2": {
            "donors": 537,
            "receipts": 710,
            "amt": 14300.12
        },
        "debate3": {
            "donors": 257,
            "receipts": 348,
            "amt": 10773.8
        },
        "debate4": {
            "donors": 1,
            "receipts": 1,
            "amt": 100
        },
        "debate5": {
            "donors": 0,
            "receipts": 0,
            "amt": 0
        },
        "debate6": {
            "donors": 0,
            "receipts": 0,
            "amt": 0
        },
        "debate7": {
            "donors": 0,
            "receipts": 0,
            "amt": 0
        },
        "inState": {
            "donors": 572,
            "receipts": 878,
            "amt": 29518.08
        },
        "outOfState": {
            "donors": 1781,
            "receipts": 2580,
            "amt": 46799.49
        },
        "prior": {
            "donors": 204,
            "receipts": 418,
            "amt": 25993.35
        },
        "loyal": {
            "donors": 158,
            "receipts": 209,
            "amt": 13341.6
        },
        "donor2016": {
            "donors": 2353,
            "receipts": 3458,
            "amt": 76317.57
        },
        "clinton2016": {
            "donors": 387,
            "receipts": 589,
            "amt": 13339.05
        },
        "sanders2016": {
            "donors": 2353,
            "receipts": 3458,
            "amt": 76317.57
        },
        "obama2012": {
            "donors": 117,
            "receipts": 175,
            "amt": 12857.08
        },
        "traitor": {
            "donors": 24,
            "receipts": 33,
            "amt": 1148.6
        },
        "elite": {
            "donors": 2298,
            "receipts": 3394,
            "amt": 75606.97
        },
        "party": {
            "donors": 2265,
            "receipts": 3358,
            "amt": 73057.57
        },
        "nationalParty": {
            "donors": 2249,
            "receipts": 3341,
            "amt": 72752.37
        },
        "stateParty": {
            "donors": 1536,
            "receipts": 2380,
            "amt": 48067.75
        },
        "localParty": {
            "donors": 300,
            "receipts": 543,
            "amt": 16162.75
        },
        "competitorEndorsement": {
            "donors": 0,
            "receipts": 0,
            "amt": 0
        },
        "congressionalEndorsement": {
            "donors": 0,
            "receipts": 0,
            "amt": 0
        },
        "senateEndorsement": {
            "donors": 0,
            "receipts": 0,
            "amt": 0
        },
        "houseEndorsement": {
            "donors": 0,
            "receipts": 0,
            "amt": 0
        }
    },
    "elite": {
        "oneDollar": {
            "donors": 1730,
            "receipts": 1730,
            "amt": 1730
        },
        "oneToTwoHundredDollars": {
            "donors": 8886,
            "receipts": 12686,
            "amt": 229439.88
        },
        "twoHundredToOneThousandDollars": {
            "donors": 522,
            "receipts": 1589,
            "amt": 196701.8
        },
        "oneThousandToTwentyEightHundredDollars": {
            "donors": 197,
            "receipts": 440,
            "amt": 261559
        },
        "twentyEightHundredDollars": {
            "donors": 222,
            "receipts": 327,
            "amt": 700749.2
        },
        "full2020PrimaryCycle": {
            "donors": 11557,
            "receipts": 16772,
            "amt": 1390179.88
        },
        "pre2019": {
            "donors": 24,
            "receipts": 34,
            "amt": 18250
        },
        "q12019": {
            "donors": 114,
            "receipts": 145,
            "amt": 153990
        },
        "q22019": {
            "donors": 10540,
            "receipts": 13843,
            "amt": 1005310.92
        },
        "q32019": {
            "donors": 1855,
            "receipts": 2746,
            "amt": 211103.76
        },
        "q42019": {
            "donors": 1,
            "receipts": 1,
            "amt": 500
        },
        "q12020": {
            "donors": 2,
            "receipts": 2,
            "amt": 1005
        },
        "debate1": {
            "donors": 9662,
            "receipts": 11740,
            "amt": 922965.47
        },
        "debate2": {
            "donors": 2401,
            "receipts": 3189,
            "amt": 293368.83
        },
        "debate3": {
            "donors": 1298,
            "receipts": 1786,
            "amt": 145440.38
        },
        "debate4": {
            "donors": 19,
            "receipts": 19,
            "amt": 8630
        },
        "debate5": {
            "donors": 1,
            "receipts": 1,
            "amt": 500
        },
        "debate6": {
            "donors": 0,
            "receipts": 0,
            "amt": 0
        },
        "debate7": {
            "donors": 0,
            "receipts": 0,
            "amt": 0
        },
        "inState": {
            "donors": 3265,
            "receipts": 4974,
            "amt": 565598.36
        },
        "outOfState": {
            "donors": 8292,
            "receipts": 11798,
            "amt": 824581.52
        },
        "prior": {
            "donors": 1423,
            "receipts": 2726,
            "amt": 768686.55
        },
        "loyal": {
            "donors": 1948,
            "receipts": 2679,
            "amt": 584144.68
        },
        "donor2016": {
            "donors": 3376,
            "receipts": 5117,
            "amt": 269226.12
        },
        "clinton2016": {
            "donors": 1443,
            "receipts": 2271,
            "amt": 193803.8
        },
        "sanders2016": {
            "donors": 2298,
            "receipts": 3394,
            "amt": 75606.97
        },
        "obama2012": {
            "donors": 473,
            "receipts": 704,
            "amt": 116370.98
        },
        "traitor": {
            "donors": 106,
            "receipts": 140,
            "amt": 10456
        },
        "elite": {
            "donors": 11557,
            "receipts": 16772,
            "amt": 1390179.88
        },
        "party": {
            "donors": 10317,
            "receipts": 15249,
            "amt": 958218.74
        },
        "nationalParty": {
            "donors": 10013,
            "receipts": 14900,
            "amt": 893242.71
        },
        "stateParty": {
            "donors": 5292,
            "receipts": 8419,
            "amt": 474014.04
        },
        "localParty": {
            "donors": 847,
            "receipts": 1567,
            "amt": 138034.44
        },
        "competitorEndorsement": {
            "donors": 0,
            "receipts": 0,
            "amt": 0
        },
        "congressionalEndorsement": {
            "donors": 0,
            "receipts": 0,
            "amt": 0
        },
        "senateEndorsement": {
            "donors": 0,
            "receipts": 0,
            "amt": 0
        },
        "houseEndorsement": {
            "donors": 0,
            "receipts": 0,
            "amt": 0
        }
    },
    "eliteParty": {
        "oneDollar": {
            "donors": 1583,
            "receipts": 1583,
            "amt": 1583
        },
        "oneToTwoHundredDollars": {
            "donors": 8110,
            "receipts": 11776,
            "amt": 202220.14
        },
        "twoHundredToOneThousandDollars": {
            "donors": 361,
            "receipts": 1342,
            "amt": 135003.6
        },
        "oneThousandToTwentyEightHundredDollars": {
            "donors": 126,
            "receipts": 342,
            "amt": 179181.8
        },
        "twentyEightHundredDollars": {
            "donors": 137,
            "receipts": 206,
            "amt": 440230.2
        },
        "full2020PrimaryCycle": {
            "donors": 10317,
            "receipts": 15249,
            "amt": 958218.74
        },
        "pre2019": {
            "donors": 21,
            "receipts": 31,
            "amt": 15250
        },
        "q12019": {
            "donors": 84,
            "receipts": 113,
            "amt": 113590
        },
        "q22019": {
            "donors": 9420,
            "receipts": 12538,
            "amt": 686284.2
        },
        "q32019": {
            "donors": 1697,
            "receipts": 2564,
            "amt": 141574.34
        },
        "q42019": {
            "donors": 1,
            "receipts": 1,
            "amt": 500
        },
        "q12020": {
            "donors": 1,
            "receipts": 1,
            "amt": 1000
        },
        "debate1": {
            "donors": 8609,
            "receipts": 10554,
            "amt": 639091.23
        },
        "debate2": {
            "donors": 2223,
            "receipts": 2981,
            "amt": 198211.49
        },
        "debate3": {
            "donors": 1187,
            "receipts": 1666,
            "amt": 98965.82
        },
        "debate4": {
            "donors": 14,
            "receipts": 14,
            "amt": 5180
        },
        "debate5": {
            "donors": 1,
            "receipts": 1,
            "amt": 500
        },
        "debate6": {
            "donors": 0,
            "receipts": 0,
            "amt": 0
        },
        "debate7": {
            "donors": 0,
            "receipts": 0,
            "amt": 0
        },
        "inState": {
            "donors": 2800,
            "receipts": 4396,
            "amt": 382769.66
        },
        "outOfState": {
            "donors": 7517,
            "receipts": 10853,
            "amt": 575449.08
        },
        "prior": {
            "donors": 1200,
            "receipts": 2419,
            "amt": 522938.55
        },
        "loyal": {
            "donors": 1329,
            "receipts": 1867,
            "amt": 293954.8
        },
        "donor2016": {
            "donors": 3310,
            "receipts": 5045,
            "amt": 251398.79
        },
        "clinton2016": {
            "donors": 1410,
            "receipts": 2236,
            "amt": 178832.87
        },
        "sanders2016": {
            "donors": 2265,
            "receipts": 3358,
            "amt": 73057.57
        },
        "obama2012": {
            "donors": 457,
            "receipts": 685,
            "amt": 112389.58
        },
        "traitor": {
            "donors": 101,
            "receipts": 135,
            "amt": 10233.8
        },
        "elite": {
            "donors": 10317,
            "receipts": 15249,
            "amt": 958218.74
        },
        "party": {
            "donors": 10317,
            "receipts": 15249,
            "amt": 958218.74
        },
        "nationalParty": {
            "donors": 10013,
            "receipts": 14900,
            "amt": 893242.71
        },
        "stateParty": {
            "donors": 5292,
            "receipts": 8419,
            "amt": 474014.04
        },
        "localParty": {
            "donors": 847,
            "receipts": 1567,
            "amt": 138034.44
        },
        "competitorEndorsement": {
            "donors": 0,
            "receipts": 0,
            "amt": 0
        },
        "congressionalEndorsement": {
            "donors": 0,
            "receipts": 0,
            "amt": 0
        },
        "senateEndorsement": {
            "donors": 0,
            "receipts": 0,
            "amt": 0
        },
        "houseEndorsement": {
            "donors": 0,
            "receipts": 0,
            "amt": 0
        }
    },
    "elitePac": {
        "oneDollar": {
            "donors": 1341,
            "receipts": 1341,
            "amt": 1341
        },
        "oneToTwoHundredDollars": {
            "donors": 7567,
            "receipts": 10977,
            "amt": 199656.24
        },
        "twoHundredToOneThousandDollars": {
            "donors": 507,
            "receipts": 1547,
            "amt": 192464.6
        },
        "oneThousandToTwentyEightHundredDollars": {
            "donors": 196,
            "receipts": 437,
            "amt": 260284
        },
        "twentyEightHundredDollars": {
            "donors": 220,
            "receipts": 324,
            "amt": 692349.2
        },
        "full2020PrimaryCycle": {
            "donors": 9831,
            "receipts": 14626,
            "amt": 1346095.04
        },
        "pre2019": {
            "donors": 24,
            "receipts": 34,
            "amt": 18250
        },
        "q12019": {
            "donors": 114,
            "receipts": 145,
            "amt": 153990
        },
        "q22019": {
            "donors": 8957,
            "receipts": 11989,
            "amt": 966005.99
        },
        "q32019": {
            "donors": 1620,
            "receipts": 2454,
            "amt": 206323.85
        },
        "q42019": {
            "donors": 1,
            "receipts": 1,
            "amt": 500
        },
        "q12020": {
            "donors": 2,
            "receipts": 2,
            "amt": 1005
        },
        "debate1": {
            "donors": 8194,
            "receipts": 10110,
            "amt": 893427.74
        },
        "debate2": {
            "donors": 2124,
            "receipts": 2871,
            "amt": 282266.33
        },
        "debate3": {
            "donors": 1126,
            "receipts": 1588,
            "amt": 141995.77
        },
        "debate4": {
            "donors": 19,
            "receipts": 19,
            "amt": 8630
        },
        "debate5": {
            "donors": 1,
            "receipts": 1,
            "amt": 500
        },
        "debate6": {
            "donors": 0,
            "receipts": 0,
            "amt": 0
        },
        "debate7": {
            "donors": 0,
            "receipts": 0,
            "amt": 0
        },
        "inState": {
            "donors": 2732,
            "receipts": 4312,
            "amt": 551690.76
        },
        "outOfState": {
            "donors": 7099,
            "receipts": 10314,
            "amt": 794404.28
        },
        "prior": {
            "donors": 1315,
            "receipts": 2594,
            "amt": 754798.15
        },
        "loyal": {
            "donors": 1399,
            "receipts": 1990,
            "amt": 561741.38
        },
        "donor2016": {
            "donors": 3138,
            "receipts": 4827,
            "amt": 264866.92
        },
        "clinton2016": {
            "donors": 1409,
            "receipts": 2229,
            "amt": 193162.6
        },
        "sanders2016": {
            "donors": 2094,
            "receipts": 3146,
            "amt": 71949.77
        },
        "obama2012": {
            "donors": 465,
            "receipts": 696,
            "amt": 116135.18
        },
        "traitor": {
            "donors": 88,
            "receipts": 121,
            "amt": 10207.2
        },
        "elite": {
            "donors": 9831,
            "receipts": 14626,
            "amt": 1346095.04
        },
        "party": {
            "donors": 8591,
            "receipts": 13103,
            "amt": 914133.9
        },
        "nationalParty": {
            "donors": 8412,
            "receipts": 12891,
            "amt": 857433.27
        },
        "stateParty": {
            "donors": 4990,
            "receipts": 8056,
            "amt": 462879.24
        },
        "localParty": {
            "donors": 827,
            "receipts": 1544,
            "amt": 137746.64
        },
        "competitorEndorsement": {
            "donors": 0,
            "receipts": 0,
            "amt": 0
        },
        "congressionalEndorsement": {
            "donors": 0,
            "receipts": 0,
            "amt": 0
        },
        "senateEndorsement": {
            "donors": 0,
            "receipts": 0,
            "amt": 0
        },
        "houseEndorsement": {
            "donors": 0,
            "receipts": 0,
            "amt": 0
        }
    }
}